{
  "timestamp": 1776607896,
  "data": {
    "accounts": {
      "group1": [
        {
          "id": "1-1",
          "fullEmail": "wdiuefgdvry@hotmail.com",
          "password": "BtC3RKPR74",
          "status": "正常",
          "checkTime": "2026-04-19 14:11:32",
          "region": "US",
          "regionName": "美区小火箭ID"
        },
        {
          "id": "1-2",
          "fullEmail": "yawezkeuidnj@hotmail.com",
          "password": "dqrVQW7WJf",
          "status": "正常",
          "checkTime": "2026-04-19 14:11:32",
          "region": "US",
          "regionName": "日区共享ID"
        },
        {
          "id": "1-3",
          "fullEmail": "forzjfnzyb@hotmail.com",
          "password": "QN2A6wxUGc",
          "status": "正常",
          "checkTime": "2026-04-19 14:11:32",
          "region": "US",
          "regionName": "美区小火箭ID"
        },
        {
          "id": "1-4",
          "fullEmail": "thomacabrera4w3@icloud.com",
          "password": "W21gKfyv8k",
          "status": "正常",
          "checkTime": "2026-04-19 14:11:32",
          "region": "US",
          "regionName": "台湾-🇨🇳"
        },
        {
          "id": "1-5",
          "fullEmail": "wendygonzagutierr1c1@icloud.com",
          "password": "ET6bYz9Hwe",
          "status": "正常",
          "checkTime": "2026-04-19 14:11:32",
          "region": "US",
          "regionName": "日本-🇯🇵"
        },
        {
          "id": "1-6",
          "fullEmail": "lehcharlotte65107@icloud.com",
          "password": "fZ7qY5edSc",
          "status": "正常",
          "checkTime": "2026-04-19 14:11:32",
          "region": "US",
          "regionName": "香港-🇨🇳"
        },
        {
          "id": "1-7",
          "fullEmail": "asromero7l4@icloud.com",
          "password": "K7R3Urdjhc",
          "status": "正常",
          "checkTime": "2026-04-19 14:11:32",
          "region": "US",
          "regionName": "韩国-🇰🇷"
        },
        {
          "id": "1-8",
          "fullEmail": "qhkn3gwvqciwz2ci@icloud.com",
          "password": "P5mJ4kg3pC",
          "status": "正常",
          "checkTime": "2026-04-19 14:11:32",
          "region": "US",
          "regionName": "美区小火箭ID"
        },
        {
          "id": "1-9",
          "fullEmail": "eggingtonkozusko36@hotmail.com",
          "password": "yE8waqP1Sy",
          "status": "正常",
          "checkTime": "2026-04-19 14:11:32",
          "region": "US",
          "regionName": "美国-🇺"
        },
        {
          "id": "1-10",
          "fullEmail": "pavelherrboldt855@hotmail.com",
          "password": "fpKRQy6KZu",
          "status": "正常",
          "checkTime": "2026-04-19 14:11:32",
          "region": "US",
          "regionName": "美国-🇺"
        },
        {
          "id": "1-11",
          "fullEmail": "christinehoward0323@looklooklook.us",
          "password": "pjM47shmA6",
          "status": "正常",
          "checkTime": "2026-04-19 14:11:36",
          "region": "US",
          "regionName": "美国"
        },
        {
          "id": "1-12",
          "fullEmail": "marknorris0514@looklooklook.us",
          "password": "rNXAKyA5cg",
          "status": "正常",
          "checkTime": "2026-04-19 14:11:36",
          "region": "US",
          "regionName": "美国"
        },
        {
          "id": "1-13",
          "fullEmail": "elizabethvalerio1202@looklooklook.us",
          "password": "R3x7FHDGFf",
          "status": "正常",
          "checkTime": "2026-04-19 14:11:36",
          "region": "US",
          "regionName": "美国"
        },
        {
          "id": "1-14",
          "fullEmail": "tiffanycampbell0727@looklooklook.us",
          "password": "tC33PZsQda",
          "status": "正常",
          "checkTime": "2026-04-19 14:11:36",
          "region": "US",
          "regionName": "美国"
        },
        {
          "id": "1-15",
          "fullEmail": "terraholt0819@looklooklook.us",
          "password": "z1FPaxh7Zj",
          "status": "正常",
          "checkTime": "2026-04-19 14:11:36",
          "region": "US",
          "regionName": "美国"
        },
        {
          "id": "1-16",
          "fullEmail": "michaelmeinhardt0910@looklooklook.us",
          "password": "csHz63Qg4R",
          "status": "正常",
          "checkTime": "2026-04-19 14:11:36",
          "region": "US",
          "regionName": "美国"
        },
        {
          "id": "1-17",
          "fullEmail": "seanruff0601@looklooklook.us",
          "password": "nMBQB3jwdP",
          "status": "正常",
          "checkTime": "2026-04-19 14:11:36",
          "region": "US",
          "regionName": "美国"
        },
        {
          "id": "1-18",
          "fullEmail": "katrinarodriguez0502@looklooklook.us",
          "password": "8TFDKzT2db",
          "status": "正常",
          "checkTime": "2026-04-19 14:11:36",
          "region": "US",
          "regionName": "美国"
        },
        {
          "id": "1-19",
          "fullEmail": "roseorth0622@looklooklook.us",
          "password": "3sSXnxMG8d",
          "status": "正常",
          "checkTime": "2026-04-19 14:11:36",
          "region": "US",
          "regionName": "美国"
        },
        {
          "id": "1-20",
          "fullEmail": "vivianzimmerman0303@looklooklook.us",
          "password": "bDcEpkr65H",
          "status": "正常",
          "checkTime": "2026-04-19 14:11:36",
          "region": "US",
          "regionName": "美国"
        },
        {
          "id": "1-21",
          "fullEmail": "merlelindo0427@looklooklook.us",
          "password": "yntT4qMWT9",
          "status": "正常",
          "checkTime": "2026-04-19 14:11:36",
          "region": "US",
          "regionName": "美国"
        },
        {
          "id": "1-22",
          "fullEmail": "mariaspann1025@looklooklook.us",
          "password": "pwrXJ6rFEu",
          "status": "正常",
          "checkTime": "2026-04-19 14:11:36",
          "region": "US",
          "regionName": "美国"
        },
        {
          "id": "1-23",
          "fullEmail": "roderickgrimes0702@looklooklook.us",
          "password": "H1MsZTVAtD",
          "status": "正常",
          "checkTime": "2026-04-19 14:11:36",
          "region": "US",
          "regionName": "美国"
        },
        {
          "id": "1-24",
          "fullEmail": "garyburton0215@looklooklook.us",
          "password": "bDzzBQFFj9",
          "status": "正常",
          "checkTime": "2026-04-19 14:11:36",
          "region": "US",
          "regionName": "美国"
        },
        {
          "id": "1-25",
          "fullEmail": "debbiedonaldson0510@looklooklook.us",
          "password": "jarEfZe8r6",
          "status": "正常",
          "checkTime": "2026-04-19 14:11:36",
          "region": "US",
          "regionName": "美国"
        },
        {
          "id": "1-26",
          "fullEmail": "beverlyfry1014@looklooklook.us",
          "password": "v6wvVYpDY9",
          "status": "正常",
          "checkTime": "2026-04-19 14:11:36",
          "region": "US",
          "regionName": "美国"
        },
        {
          "id": "1-27",
          "fullEmail": "victoriamangrum0819@looklooklook.us",
          "password": "vVCpBp2NKT",
          "status": "正常",
          "checkTime": "2026-04-19 14:11:36",
          "region": "US",
          "regionName": "美国"
        },
        {
          "id": "1-28",
          "fullEmail": "stevelando1128@looklooklook.us",
          "password": "zTDHfEQf9Y",
          "status": "正常",
          "checkTime": "2026-04-19 14:11:36",
          "region": "US",
          "regionName": "美国"
        },
        {
          "id": "1-29",
          "fullEmail": "cynthiarodrigues1111@looklooklook.us",
          "password": "tcw3ESDYVr",
          "status": "正常",
          "checkTime": "2026-04-19 14:11:36",
          "region": "US",
          "regionName": "美国"
        },
        {
          "id": "1-30",
          "fullEmail": "maryloufigueroa1008@looklooklook.us",
          "password": "b4nMGZv9bs",
          "status": "正常",
          "checkTime": "2026-04-19 14:11:36",
          "region": "US",
          "regionName": "美国"
        },
        {
          "id": "1-31",
          "fullEmail": "paulpeek0701@looklooklook.us",
          "password": "c6vMJT67mQ",
          "status": "正常",
          "checkTime": "2026-04-19 14:11:36",
          "region": "US",
          "regionName": "美国"
        },
        {
          "id": "1-32",
          "fullEmail": "rachelhernandez1010@looklooklook.us",
          "password": "Sw98GKaTV1",
          "status": "正常",
          "checkTime": "2026-04-19 14:11:36",
          "region": "US",
          "regionName": "美国"
        },
        {
          "id": "1-33",
          "fullEmail": "kennethfernandez0501@looklooklook.us",
          "password": "seFfuMKjR5",
          "status": "正常",
          "checkTime": "2026-04-19 14:11:36",
          "region": "US",
          "regionName": "美国"
        },
        {
          "id": "1-34",
          "fullEmail": "consuelapearson0628@looklooklook.us",
          "password": "NX4Hy3MCdt",
          "status": "正常",
          "checkTime": "2026-04-19 14:11:36",
          "region": "US",
          "regionName": "美国"
        },
        {
          "id": "1-35",
          "fullEmail": "mriryybpw3ytmenpdgnw@icloud.com",
          "password": "YqB6vrSHGq",
          "status": "正常",
          "checkTime": "2026-04-19 14:11:36",
          "region": "US",
          "regionName": "美国"
        },
        {
          "id": "1-36",
          "fullEmail": "fi6ef2rrocwi4aejm0ei@icloud.com",
          "password": "SzSBmezX66",
          "status": "正常",
          "checkTime": "2026-04-19 14:11:36",
          "region": "US",
          "regionName": "美国"
        },
        {
          "id": "1-37",
          "fullEmail": "zd033zjzodhcgn6h0d@icloud.com",
          "password": "SsuaHE8D8a",
          "status": "正常",
          "checkTime": "2026-04-19 14:11:36",
          "region": "US",
          "regionName": "美国"
        },
        {
          "id": "1-38",
          "fullEmail": "nbrvc11222@hotmail.com",
          "password": "RVdE5JjDWs",
          "status": "正常",
          "checkTime": "2026-04-19 14:11:36",
          "region": "US",
          "regionName": "美国"
        },
        {
          "id": "1-39",
          "fullEmail": "dpkjknd45561@hotmail.com",
          "password": "UnM6JFrANs",
          "status": "正常",
          "checkTime": "2026-04-19 14:11:36",
          "region": "US",
          "regionName": "美国"
        },
        {
          "id": "1-40",
          "fullEmail": "sheznjbvd@hotmail.com",
          "password": "TDgTsw2PMug6",
          "status": "正常",
          "checkTime": "2026-04-19 14:11:36",
          "region": "US",
          "regionName": "美国"
        },
        {
          "id": "1-41",
          "fullEmail": "juflgcjql@hotmail.com",
          "password": "TDFfUC7rEtGg",
          "status": "正常",
          "checkTime": "2026-04-19 14:11:36",
          "region": "US",
          "regionName": "美国"
        },
        {
          "id": "1-42",
          "fullEmail": "imwnoycjh@hotmail.com",
          "password": "TDmqWkQ6nsZ2",
          "status": "正常",
          "checkTime": "2026-04-19 14:11:36",
          "region": "VN",
          "regionName": "越南"
        },
        {
          "id": "1-43",
          "fullEmail": "czbjilstncu@hotmail.com",
          "password": "TDsgdrNMvs3C",
          "status": "正常",
          "checkTime": "2026-04-19 14:11:36",
          "region": "US",
          "regionName": "设置"
        },
        {
          "id": "1-44",
          "fullEmail": "iijluqbfkeek@hotmail.com",
          "password": "TD9CHZvMnNZS",
          "status": "正常",
          "checkTime": "2026-04-19 14:11:36",
          "region": "US",
          "regionName": "中国大陆"
        },
        {
          "id": "1-45",
          "fullEmail": "rgkppwnoi@hotmail.com",
          "password": "TDPm2Z1cRndE",
          "status": "正常",
          "checkTime": "2026-04-19 14:11:36",
          "region": "US",
          "regionName": "美国"
        },
        {
          "id": "1-46",
          "fullEmail": "pztiyijliya@hotmail.com",
          "password": "TDuSaQynjAM1",
          "status": "正常",
          "checkTime": "2026-04-19 14:11:36",
          "region": "US",
          "regionName": "美国"
        },
        {
          "id": "1-47",
          "fullEmail": "qsvfcnbhxdk@hotmail.com",
          "password": "TDn6Mf3rsaK6",
          "status": "正常",
          "checkTime": "2026-04-19 14:11:36",
          "region": "US",
          "regionName": "美国"
        },
        {
          "id": "1-48",
          "fullEmail": "vlsxjriqmgywp@hotmail.com",
          "password": "TDSRS6pWcarb",
          "status": "正常",
          "checkTime": "2026-04-19 14:11:36",
          "region": "VN",
          "regionName": "越南"
        }
      ],
      "group2": []
    },
    "vpn_ads": [
      {
        "id": "vpn-1",
        "name": "宝可梦VPN",
        "features": "新起之秀。本推广链接注册后，每月赠送60G流量。IP稳定且干净，不会因为IP脏被封号。本月白嫖码：鸡你太美  ",
        "url": "https://web4.52pokemon.cc/register?code=qzhkvhLk",
        "gradient": "135deg, #667eea 0%, #764ba2 100%",
        "status": "active"
      },
      {
        "id": "vpn-2",
        "name": "万达云：严测推荐",
        "features": "(36地区，90+节点）海外团队，安全、稳定、极速（支持试用，9折码：wandayun）",
        "url": "https://link.wdyserver.com/register?code=HCmXeijh",
        "gradient": "135deg, #667eea 0%, #764ba2 100%",
        "status": "active"
      },
      {
        "id": "vpn-3",
        "name": "红杏云VPN",
        "features": "老牌VPN提供商了。虽然IP不如宝可梦干净，但是。胜在网速和稳定性和宝可梦旗鼓相当。<br>八折优惠码：hx2025",
        "url": "https://hongxing.one/web/#/login?code=NOGK4o3y",
        "gradient": "135deg, #667eea 0%, #764ba2 100%",
        "status": "active"
      },
      {
        "id": "vpn-4",
        "name": "青云梯：严测推荐",
        "features": "（16地区，70+节点）海外团队，安全稳定极速（月8.5折码：qyt85，年8折码：qyt80）",
        "url": "https://ivt02.qytaff.cc/register?aff=9AOwCUUP",
        "gradient": "135deg, #667eea 0%, #764ba2 100%",
        "status": "active"
      },
      {
        "id": "vpn-5",
        "name": "涅槃云：严测推荐",
        "features": "（16地区，30+节点）严测推荐，海外团队，安全、稳定、极速（9折优惠券：qsy99）",
        "url": "https://theme.revival.baby/register?code=z2B4HAcv",
        "gradient": "135deg, #667eea 0%, #764ba2 100%",
        "status": "active"
      },
      {
        "id": "vpn-6",
        "name": "红杏：严测推荐",
        "features": "(23地区，70+节点）海外团队，安全、稳定、极速（注册即送：50G/30天）（8折优惠码：hongxing666）",
        "url": "https://www.xn--8qv123c.co/auth/register?code=z6kV78AV",
        "gradient": "135deg, #667eea 0%, #764ba2 100%",
        "status": "active"
      },
      {
        "id": "vpn-7",
        "name": "快连VPN：严测推荐",
        "features": "六年老品牌，2000万人的选择，人工客服时时在线，IP干净，速度稳定，价格便宜，通过本站推荐，可以先用再买<br>并且赠送购买时长的20%<br>9折优惠码：380269387",
        "url": "https://8m5tnb.onelink.me/0Iq2/up2p5vb6",
        "gradient": "135deg, #667eea 0%, #764ba2 100%",
        "status": "active"
      }
    ]
  }
}