{
  "timestamp": 1780636059,
  "data": {
    "accounts": {
      "group1": [
        {
          "id": "1-1",
          "fullEmail": "NicoleYates6661@outlook.com",
          "password": "Pjmp7Ghp4g",
          "status": "正常",
          "checkTime": "2026-06-05 05:07:36",
          "region": "KR",
          "regionName": "韩国"
        },
        {
          "id": "1-2",
          "fullEmail": "DavidPerez4266@hotmail.com",
          "password": "d1brknBqJc",
          "status": "正常",
          "checkTime": "2026-06-05 05:07:36",
          "region": "TW",
          "regionName": "台湾"
        },
        {
          "id": "1-3",
          "fullEmail": "WhitneyHarding2964@outlook.com",
          "password": "7T7Q8f4GWy",
          "status": "正常",
          "checkTime": "2026-06-05 05:07:36",
          "region": "US",
          "regionName": "美国-🇺"
        },
        {
          "id": "1-4",
          "fullEmail": "HenryJones4163@outlook.com",
          "password": "bjWwt39xQe",
          "status": "正常",
          "checkTime": "2026-06-05 05:07:36",
          "region": "US",
          "regionName": "日本-🇯🇵"
        },
        {
          "id": "1-5",
          "fullEmail": "JustinRamirez5475Oco@outlook.com",
          "password": "Mg980409",
          "status": "正常",
          "checkTime": "2026-06-05 05:07:36",
          "region": "US",
          "regionName": "韩国-🇰🇷"
        },
        {
          "id": "1-6",
          "fullEmail": "AmandaPerez4637@outlook.com",
          "password": "ddND2683",
          "status": "正常",
          "checkTime": "2026-06-05 05:07:36",
          "region": "US",
          "regionName": "美国-🇺"
        },
        {
          "id": "1-7",
          "fullEmail": "AnthonyHiggins6333@outlook.com",
          "password": "kHJejUXNE7",
          "status": "正常",
          "checkTime": "2026-06-05 05:07:36",
          "region": "US",
          "regionName": "香港-🇨🇳"
        },
        {
          "id": "1-8",
          "fullEmail": "FeliciaWilliamson9137Ta1@outlook.com",
          "password": "YUkR7cg5c3",
          "status": "正常",
          "checkTime": "2026-06-05 05:07:36",
          "region": "US",
          "regionName": "香港-🇨🇳"
        },
        {
          "id": "1-9",
          "fullEmail": "MatthewPruitt3496@outlook.com",
          "password": "Wr1S4P4kF3",
          "status": "正常",
          "checkTime": "2026-06-05 05:07:36",
          "region": "US",
          "regionName": "韩国-🇰🇷"
        },
        {
          "id": "1-10",
          "fullEmail": "StevenEverett9567fnu2@outlook.com",
          "password": "ddND2683",
          "status": "正常",
          "checkTime": "2026-06-05 05:07:36",
          "region": "US",
          "regionName": "美国-🇺"
        },
        {
          "id": "1-11",
          "fullEmail": "CesarHarrington8181PJ@outlook.com",
          "password": "ddND2683",
          "status": "正常",
          "checkTime": "2026-06-05 05:07:36",
          "region": "US",
          "regionName": "美国-🇺"
        },
        {
          "id": "1-12",
          "fullEmail": "quodonnell@gmail.com",
          "password": "Dd10096da",
          "status": "正常",
          "checkTime": "2026-06-05 05:07:39",
          "region": "US",
          "regionName": "美区"
        },
        {
          "id": "1-13",
          "fullEmail": "DeborazpiHarr967@icloud.com",
          "password": "x5Qt9ch9m9",
          "status": "正常",
          "checkTime": "2026-06-05 05:07:39",
          "region": "US",
          "regionName": "美区"
        },
        {
          "id": "1-14",
          "fullEmail": "jarvarisrivetteuf3409@gmail.com",
          "password": "VG7j2eeg4C",
          "status": "正常",
          "checkTime": "2026-06-05 05:07:39",
          "region": "US",
          "regionName": "美区"
        },
        {
          "id": "1-15",
          "fullEmail": "AllenMilliepyl879@gmail.com",
          "password": "44s41NP3MD5pf3",
          "status": "正常",
          "checkTime": "2026-06-05 05:07:39",
          "region": "US",
          "regionName": "美区"
        },
        {
          "id": "1-16",
          "fullEmail": "BettyGarcia5be56@gmail.com",
          "password": "44s4nrRa3yZnJ5",
          "status": "正常",
          "checkTime": "2026-06-05 05:07:39",
          "region": "US",
          "regionName": "美区"
        },
        {
          "id": "1-17",
          "fullEmail": "LouieGraybeal643464@hotmail.com",
          "password": "d3tmfx1Uh6",
          "status": "正常",
          "checkTime": "2026-06-05 05:07:39",
          "region": "US",
          "regionName": "美国"
        },
        {
          "id": "1-18",
          "fullEmail": "HaroldHenseler961538@hotmail.com",
          "password": "hveAfMw4pm",
          "status": "正常",
          "checkTime": "2026-06-05 05:07:39",
          "region": "US",
          "regionName": "美国"
        },
        {
          "id": "1-19",
          "fullEmail": "HaydenSloan596118@hotmail.com",
          "password": "KY9dJGRrwe",
          "status": "正常",
          "checkTime": "2026-06-05 05:07:39",
          "region": "US",
          "regionName": "美国"
        },
        {
          "id": "1-20",
          "fullEmail": "nmpm1328@hhl123.club",
          "password": "21BsWEEGJj",
          "status": "正常",
          "checkTime": "2026-06-05 05:07:39",
          "region": "US",
          "regionName": "美国"
        },
        {
          "id": "1-21",
          "fullEmail": "SalliePuckett82746@hotmail.com",
          "password": "PnTFZ1NY4n",
          "status": "正常",
          "checkTime": "2026-06-05 05:07:39",
          "region": "US",
          "regionName": "美国"
        },
        {
          "id": "1-22",
          "fullEmail": "WillardFerebee8670@hotmail.com",
          "password": "su19PSUtZv",
          "status": "正常",
          "checkTime": "2026-06-05 05:07:39",
          "region": "US",
          "regionName": "美国"
        },
        {
          "id": "1-23",
          "fullEmail": "LuisColes36428@hotmail.com",
          "password": "Cme6Mbj2xU",
          "status": "正常",
          "checkTime": "2026-06-05 05:07:39",
          "region": "US",
          "regionName": "美国"
        },
        {
          "id": "1-24",
          "fullEmail": "AndreaHadfield0260@hotmail.com",
          "password": "3C9EYpebKV",
          "status": "正常",
          "checkTime": "2026-06-05 05:07:39",
          "region": "US",
          "regionName": "美国"
        },
        {
          "id": "1-25",
          "fullEmail": "DavidBoyle32619@hotmail.com",
          "password": "KSjPwW6gn9",
          "status": "正常",
          "checkTime": "2026-06-05 05:07:39",
          "region": "US",
          "regionName": "美国"
        },
        {
          "id": "1-26",
          "fullEmail": "FriedaHyde5615@hotmail.com",
          "password": "aFQSFTrtC6",
          "status": "正常",
          "checkTime": "2026-06-05 05:07:39",
          "region": "US",
          "regionName": "美国"
        },
        {
          "id": "1-27",
          "fullEmail": "KatrinaMcbride72693@hotmail.com",
          "password": "1t2Pt8mdCc",
          "status": "正常",
          "checkTime": "2026-06-05 05:07:39",
          "region": "US",
          "regionName": "美国"
        },
        {
          "id": "1-28",
          "fullEmail": "MaryLawson711719@hotmail.com",
          "password": "xQenqH1r6G",
          "status": "正常",
          "checkTime": "2026-06-05 05:07:39",
          "region": "US",
          "regionName": "美国"
        },
        {
          "id": "1-29",
          "fullEmail": "GayleKing8548@hotmail.com",
          "password": "4f8wgKwNay",
          "status": "正常",
          "checkTime": "2026-06-05 05:07:39",
          "region": "US",
          "regionName": "美国"
        },
        {
          "id": "1-30",
          "fullEmail": "JoshuaMorrell570361@hotmail.com",
          "password": "t5E2E6qfyK",
          "status": "正常",
          "checkTime": "2026-06-05 05:07:39",
          "region": "US",
          "regionName": "美国"
        },
        {
          "id": "1-31",
          "fullEmail": "RichardBielecki322845@hotmail.com",
          "password": "TATWan34m4",
          "status": "正常",
          "checkTime": "2026-06-05 05:07:39",
          "region": "US",
          "regionName": "美国"
        },
        {
          "id": "1-32",
          "fullEmail": "BrianaWalter819028@hotmail.com",
          "password": "sXn4wTMAQ8",
          "status": "正常",
          "checkTime": "2026-06-05 05:07:39",
          "region": "US",
          "regionName": "美国"
        },
        {
          "id": "1-33",
          "fullEmail": "JenniferMcgregor586495@hotmail.com",
          "password": "ngCSkXRf9w",
          "status": "正常",
          "checkTime": "2026-06-05 05:07:39",
          "region": "US",
          "regionName": "美国"
        },
        {
          "id": "1-34",
          "fullEmail": "DannyDurr84057@hotmail.com",
          "password": "5KrPtAMgE7",
          "status": "正常",
          "checkTime": "2026-06-05 05:07:39",
          "region": "US",
          "regionName": "美国"
        },
        {
          "id": "1-35",
          "fullEmail": "MarilynBarber8560@hotmail.com",
          "password": "aY87N3mkDz",
          "status": "正常",
          "checkTime": "2026-06-05 05:07:39",
          "region": "US",
          "regionName": "美国"
        },
        {
          "id": "1-36",
          "fullEmail": "WilliamVega56824@hotmail.com",
          "password": "nnH6Qud3Rh",
          "status": "正常",
          "checkTime": "2026-06-05 05:07:39",
          "region": "US",
          "regionName": "美国"
        },
        {
          "id": "1-37",
          "fullEmail": "AdysonKeith3668@hotmail.com",
          "password": "TWHtB9MN9m",
          "status": "正常",
          "checkTime": "2026-06-05 05:07:39",
          "region": "US",
          "regionName": "美国"
        },
        {
          "id": "1-38",
          "fullEmail": "JosiahWoolett1724@hotmail.com",
          "password": "NwA1SAXYc6",
          "status": "正常",
          "checkTime": "2026-06-05 05:07:39",
          "region": "US",
          "regionName": "美国"
        }
      ],
      "group2": []
    },
    "vpn_ads": [
      {
        "id": "vpn-1",
        "name": "宝可梦VPN",
        "features": "新起之秀。本推广链接注册后，每月赠送60G流量。IP稳定且干净，不会因为IP脏被封号。本月白嫖码：鸡你太美  ",
        "url": "https://web4.52pokemon.cc/register?code=qzhkvhLk",
        "gradient": "135deg, #667eea 0%, #764ba2 100%",
        "status": "active"
      },
      {
        "id": "vpn-2",
        "name": "万达云：严测推荐",
        "features": "(36地区，90+节点）海外团队，安全、稳定、极速（支持试用，9折码：wandayun）",
        "url": "https://link.wdyserver.com/register?code=HCmXeijh",
        "gradient": "135deg, #667eea 0%, #764ba2 100%",
        "status": "active"
      },
      {
        "id": "vpn-3",
        "name": "红杏云VPN",
        "features": "老牌VPN提供商了。虽然IP不如宝可梦干净，但是。胜在网速和稳定性和宝可梦旗鼓相当。<br>八折优惠码：hx2025",
        "url": "https://hongxing.one/web/#/login?code=NOGK4o3y",
        "gradient": "135deg, #667eea 0%, #764ba2 100%",
        "status": "active"
      },
      {
        "id": "vpn-4",
        "name": "青云梯：严测推荐",
        "features": "（16地区，70+节点）海外团队，安全稳定极速（月8.5折码：qyt85，年8折码：qyt80）",
        "url": "https://ivt02.qytaff.cc/register?aff=9AOwCUUP",
        "gradient": "135deg, #667eea 0%, #764ba2 100%",
        "status": "active"
      },
      {
        "id": "vpn-5",
        "name": "涅槃云：严测推荐",
        "features": "（16地区，30+节点）严测推荐，海外团队，安全、稳定、极速（9折优惠券：qsy99）",
        "url": "https://theme.revival.baby/register?code=z2B4HAcv",
        "gradient": "135deg, #667eea 0%, #764ba2 100%",
        "status": "active"
      },
      {
        "id": "vpn-6",
        "name": "红杏：严测推荐",
        "features": "(23地区，70+节点）海外团队，安全、稳定、极速（注册即送：50G/30天）（8折优惠码：hongxing666）",
        "url": "https://www.xn--8qv123c.co/auth/register?code=z6kV78AV",
        "gradient": "135deg, #667eea 0%, #764ba2 100%",
        "status": "active"
      },
      {
        "id": "vpn-7",
        "name": "快连VPN：严测推荐",
        "features": "六年老品牌，2000万人的选择，人工客服时时在线，IP干净，速度稳定，价格便宜，通过本站推荐，可以先用再买<br>并且赠送购买时长的20%<br>9折优惠码：380269387",
        "url": "https://8m5tnb.onelink.me/0Iq2/up2p5vb6",
        "gradient": "135deg, #667eea 0%, #764ba2 100%",
        "status": "active"
      }
    ]
  }
}