{
  "total": 48,
  "update_time": "2026-04-17 23:08:59",
  "source_url": "https://tkbaohe.com/Shadowrocket/",
  "source_urls": [
    "https://tkbaohe.com/Shadowrocket/",
    "https://ccbaohe.com/appleID/"
  ],
  "accounts": [
    {
      "account": "wd***@hotmail.com",
      "email": "wdiuefgdvry@hotmail.com",
      "fullEmail": "wdiuefgdvry@hotmail.com",
      "password": "BtC3RKPR74",
      "region": "US",
      "regionName": "美区小火箭ID",
      "status": "正常",
      "checkTime": "2026-04-17 23:08:56",
      "crawl_time": "2026-04-17 23:08:56",
      "source_page": "https://tkbaohe.com/Shadowrocket/"
    },
    {
      "account": "ya***@hotmail.com",
      "email": "yawezkeuidnj@hotmail.com",
      "fullEmail": "yawezkeuidnj@hotmail.com",
      "password": "dqrVQW7WJf",
      "region": "US",
      "regionName": "日区共享ID",
      "status": "正常",
      "checkTime": "2026-04-17 23:08:56",
      "crawl_time": "2026-04-17 23:08:56",
      "source_page": "https://tkbaohe.com/Shadowrocket/"
    },
    {
      "account": "fo***@hotmail.com",
      "email": "forzjfnzyb@hotmail.com",
      "fullEmail": "forzjfnzyb@hotmail.com",
      "password": "QN2A6wxUGc",
      "region": "US",
      "regionName": "美区小火箭ID",
      "status": "正常",
      "checkTime": "2026-04-17 23:08:56",
      "crawl_time": "2026-04-17 23:08:56",
      "source_page": "https://tkbaohe.com/Shadowrocket/"
    },
    {
      "account": "th***@icloud.com",
      "email": "thomacabrera4w3@icloud.com",
      "fullEmail": "thomacabrera4w3@icloud.com",
      "password": "W21gKfyv8k",
      "region": "US",
      "regionName": "台湾-🇨🇳",
      "status": "正常",
      "checkTime": "2026-04-17 23:08:56",
      "crawl_time": "2026-04-17 23:08:56",
      "source_page": "https://tkbaohe.com/Shadowrocket/"
    },
    {
      "account": "we***@icloud.com",
      "email": "wendygonzagutierr1c1@icloud.com",
      "fullEmail": "wendygonzagutierr1c1@icloud.com",
      "password": "ET6bYz9Hwe",
      "region": "US",
      "regionName": "日本-🇯🇵",
      "status": "正常",
      "checkTime": "2026-04-17 23:08:56",
      "crawl_time": "2026-04-17 23:08:56",
      "source_page": "https://tkbaohe.com/Shadowrocket/"
    },
    {
      "account": "le***@icloud.com",
      "email": "lehcharlotte65107@icloud.com",
      "fullEmail": "lehcharlotte65107@icloud.com",
      "password": "fZ7qY5edSc",
      "region": "US",
      "regionName": "香港-🇨🇳",
      "status": "正常",
      "checkTime": "2026-04-17 23:08:56",
      "crawl_time": "2026-04-17 23:08:56",
      "source_page": "https://tkbaohe.com/Shadowrocket/"
    },
    {
      "account": "as***@icloud.com",
      "email": "asromero7l4@icloud.com",
      "fullEmail": "asromero7l4@icloud.com",
      "password": "K7R3Urdjhc",
      "region": "US",
      "regionName": "韩国-🇰🇷",
      "status": "正常",
      "checkTime": "2026-04-17 23:08:56",
      "crawl_time": "2026-04-17 23:08:56",
      "source_page": "https://tkbaohe.com/Shadowrocket/"
    },
    {
      "account": "qh***@icloud.com",
      "email": "qhkn3gwvqciwz2ci@icloud.com",
      "fullEmail": "qhkn3gwvqciwz2ci@icloud.com",
      "password": "P5mJ4kg3pC",
      "region": "US",
      "regionName": "美区小火箭ID",
      "status": "正常",
      "checkTime": "2026-04-17 23:08:56",
      "crawl_time": "2026-04-17 23:08:56",
      "source_page": "https://tkbaohe.com/Shadowrocket/"
    },
    {
      "account": "eg***@hotmail.com",
      "email": "eggingtonkozusko36@hotmail.com",
      "fullEmail": "eggingtonkozusko36@hotmail.com",
      "password": "yE8waqP1Sy",
      "region": "US",
      "regionName": "美国-🇺",
      "status": "正常",
      "checkTime": "2026-04-17 23:08:56",
      "crawl_time": "2026-04-17 23:08:56",
      "source_page": "https://tkbaohe.com/Shadowrocket/"
    },
    {
      "account": "pa***@hotmail.com",
      "email": "pavelherrboldt855@hotmail.com",
      "fullEmail": "pavelherrboldt855@hotmail.com",
      "password": "fpKRQy6KZu",
      "region": "US",
      "regionName": "美国-🇺",
      "status": "正常",
      "checkTime": "2026-04-17 23:08:56",
      "crawl_time": "2026-04-17 23:08:56",
      "source_page": "https://tkbaohe.com/Shadowrocket/"
    },
    {
      "account": "te***@looklooklook.us",
      "email": "terrybrennan0909@looklooklook.us",
      "fullEmail": "terrybrennan0909@looklooklook.us",
      "password": "KkuT7qkQPn",
      "region": "US",
      "regionName": "美国",
      "status": "正常",
      "checkTime": "2026-04-17 23:08:59",
      "crawl_time": "2026-04-17 23:08:59",
      "source_page": "https://ccbaohe.com/appleID/"
    },
    {
      "account": "er***@looklooklook.us",
      "email": "erictorres0618@looklooklook.us",
      "fullEmail": "erictorres0618@looklooklook.us",
      "password": "G6sb4rAtW2",
      "region": "US",
      "regionName": "美国",
      "status": "正常",
      "checkTime": "2026-04-17 23:08:59",
      "crawl_time": "2026-04-17 23:08:59",
      "source_page": "https://ccbaohe.com/appleID/"
    },
    {
      "account": "he***@looklooklook.us",
      "email": "henrythomas0115@looklooklook.us",
      "fullEmail": "henrythomas0115@looklooklook.us",
      "password": "nfeSpNjF6A",
      "region": "US",
      "regionName": "美国",
      "status": "正常",
      "checkTime": "2026-04-17 23:08:59",
      "crawl_time": "2026-04-17 23:08:59",
      "source_page": "https://ccbaohe.com/appleID/"
    },
    {
      "account": "sh***@looklooklook.us",
      "email": "sherripeace0907@looklooklook.us",
      "fullEmail": "sherripeace0907@looklooklook.us",
      "password": "KaMmknD9k7",
      "region": "US",
      "regionName": "美国",
      "status": "正常",
      "checkTime": "2026-04-17 23:08:59",
      "crawl_time": "2026-04-17 23:08:59",
      "source_page": "https://ccbaohe.com/appleID/"
    },
    {
      "account": "je***@looklooklook.us",
      "email": "jennifergetz1002@looklooklook.us",
      "fullEmail": "jennifergetz1002@looklooklook.us",
      "password": "Yw4RYsaypr",
      "region": "US",
      "regionName": "美国",
      "status": "正常",
      "checkTime": "2026-04-17 23:08:59",
      "crawl_time": "2026-04-17 23:08:59",
      "source_page": "https://ccbaohe.com/appleID/"
    },
    {
      "account": "ki***@looklooklook.us",
      "email": "kimsmith1126@looklooklook.us",
      "fullEmail": "kimsmith1126@looklooklook.us",
      "password": "8YHtEAVb1y",
      "region": "US",
      "regionName": "美国",
      "status": "正常",
      "checkTime": "2026-04-17 23:08:59",
      "crawl_time": "2026-04-17 23:08:59",
      "source_page": "https://ccbaohe.com/appleID/"
    },
    {
      "account": "sh***@looklooklook.us",
      "email": "sharisantana0409@looklooklook.us",
      "fullEmail": "sharisantana0409@looklooklook.us",
      "password": "pN1mGKy1VB",
      "region": "US",
      "regionName": "美国",
      "status": "正常",
      "checkTime": "2026-04-17 23:08:59",
      "crawl_time": "2026-04-17 23:08:59",
      "source_page": "https://ccbaohe.com/appleID/"
    },
    {
      "account": "ch***@looklooklook.us",
      "email": "charlesvanmeter0413@looklooklook.us",
      "fullEmail": "charlesvanmeter0413@looklooklook.us",
      "password": "tWH97MUmKv",
      "region": "US",
      "regionName": "美国",
      "status": "正常",
      "checkTime": "2026-04-17 23:08:59",
      "crawl_time": "2026-04-17 23:08:59",
      "source_page": "https://ccbaohe.com/appleID/"
    },
    {
      "account": "jo***@looklooklook.us",
      "email": "johnsavage1005@looklooklook.us",
      "fullEmail": "johnsavage1005@looklooklook.us",
      "password": "VkaPsH5bHT",
      "region": "US",
      "regionName": "美国",
      "status": "正常",
      "checkTime": "2026-04-17 23:08:59",
      "crawl_time": "2026-04-17 23:08:59",
      "source_page": "https://ccbaohe.com/appleID/"
    },
    {
      "account": "ro***@looklooklook.us",
      "email": "roderickgrimes0702@looklooklook.us",
      "fullEmail": "roderickgrimes0702@looklooklook.us",
      "password": "528NB42wQP",
      "region": "US",
      "regionName": "美国",
      "status": "正常",
      "checkTime": "2026-04-17 23:08:59",
      "crawl_time": "2026-04-17 23:08:59",
      "source_page": "https://ccbaohe.com/appleID/"
    },
    {
      "account": "ga***@looklooklook.us",
      "email": "garyburton0215@looklooklook.us",
      "fullEmail": "garyburton0215@looklooklook.us",
      "password": "DKuw6MRB18",
      "region": "US",
      "regionName": "美国",
      "status": "正常",
      "checkTime": "2026-04-17 23:08:59",
      "crawl_time": "2026-04-17 23:08:59",
      "source_page": "https://ccbaohe.com/appleID/"
    },
    {
      "account": "de***@looklooklook.us",
      "email": "debbiedonaldson0510@looklooklook.us",
      "fullEmail": "debbiedonaldson0510@looklooklook.us",
      "password": "7hSME286Mu",
      "region": "US",
      "regionName": "美国",
      "status": "正常",
      "checkTime": "2026-04-17 23:08:59",
      "crawl_time": "2026-04-17 23:08:59",
      "source_page": "https://ccbaohe.com/appleID/"
    },
    {
      "account": "vi***@looklooklook.us",
      "email": "victoriamangrum0819@looklooklook.us",
      "fullEmail": "victoriamangrum0819@looklooklook.us",
      "password": "cWKa5TvyrH",
      "region": "US",
      "regionName": "美国",
      "status": "正常",
      "checkTime": "2026-04-17 23:08:59",
      "crawl_time": "2026-04-17 23:08:59",
      "source_page": "https://ccbaohe.com/appleID/"
    },
    {
      "account": "jo***@looklooklook.us",
      "email": "johnisaac1015@looklooklook.us",
      "fullEmail": "johnisaac1015@looklooklook.us",
      "password": "2gvkvmyxCj",
      "region": "US",
      "regionName": "美国",
      "status": "正常",
      "checkTime": "2026-04-17 23:08:59",
      "crawl_time": "2026-04-17 23:08:59",
      "source_page": "https://ccbaohe.com/appleID/"
    },
    {
      "account": "st***@looklooklook.us",
      "email": "stevelando1128@looklooklook.us",
      "fullEmail": "stevelando1128@looklooklook.us",
      "password": "k4WDhNVgrP",
      "region": "US",
      "regionName": "美国",
      "status": "正常",
      "checkTime": "2026-04-17 23:08:59",
      "crawl_time": "2026-04-17 23:08:59",
      "source_page": "https://ccbaohe.com/appleID/"
    },
    {
      "account": "ma***@looklooklook.us",
      "email": "markhunt0416@looklooklook.us",
      "fullEmail": "markhunt0416@looklooklook.us",
      "password": "j3C2rnv5sX",
      "region": "US",
      "regionName": "美国",
      "status": "正常",
      "checkTime": "2026-04-17 23:08:59",
      "crawl_time": "2026-04-17 23:08:59",
      "source_page": "https://ccbaohe.com/appleID/"
    },
    {
      "account": "wa***@looklooklook.us",
      "email": "waynemcdonald0901@looklooklook.us",
      "fullEmail": "waynemcdonald0901@looklooklook.us",
      "password": "zDEmmz83Vh",
      "region": "US",
      "regionName": "美国",
      "status": "正常",
      "checkTime": "2026-04-17 23:08:59",
      "crawl_time": "2026-04-17 23:08:59",
      "source_page": "https://ccbaohe.com/appleID/"
    },
    {
      "account": "pa***@looklooklook.us",
      "email": "paulwright1110@looklooklook.us",
      "fullEmail": "paulwright1110@looklooklook.us",
      "password": "AHE1eKpKqh",
      "region": "US",
      "regionName": "美国",
      "status": "正常",
      "checkTime": "2026-04-17 23:08:59",
      "crawl_time": "2026-04-17 23:08:59",
      "source_page": "https://ccbaohe.com/appleID/"
    },
    {
      "account": "da***@looklooklook.us",
      "email": "darlenejohnson0718@looklooklook.us",
      "fullEmail": "darlenejohnson0718@looklooklook.us",
      "password": "UUWdnk468N",
      "region": "US",
      "regionName": "美国",
      "status": "正常",
      "checkTime": "2026-04-17 23:08:59",
      "crawl_time": "2026-04-17 23:08:59",
      "source_page": "https://ccbaohe.com/appleID/"
    },
    {
      "account": "ma***@looklooklook.us",
      "email": "maryloufigueroa1008@looklooklook.us",
      "fullEmail": "maryloufigueroa1008@looklooklook.us",
      "password": "rH7t7c4rHc",
      "region": "US",
      "regionName": "美国",
      "status": "正常",
      "checkTime": "2026-04-17 23:08:59",
      "crawl_time": "2026-04-17 23:08:59",
      "source_page": "https://ccbaohe.com/appleID/"
    },
    {
      "account": "pa***@looklooklook.us",
      "email": "paulpeek0701@looklooklook.us",
      "fullEmail": "paulpeek0701@looklooklook.us",
      "password": "HB7zaANdGq",
      "region": "US",
      "regionName": "美国",
      "status": "正常",
      "checkTime": "2026-04-17 23:08:59",
      "crawl_time": "2026-04-17 23:08:59",
      "source_page": "https://ccbaohe.com/appleID/"
    },
    {
      "account": "ga***@looklooklook.us",
      "email": "garytoll0811@looklooklook.us",
      "fullEmail": "garytoll0811@looklooklook.us",
      "password": "cNk7HyxJsY",
      "region": "US",
      "regionName": "美国",
      "status": "正常",
      "checkTime": "2026-04-17 23:08:59",
      "crawl_time": "2026-04-17 23:08:59",
      "source_page": "https://ccbaohe.com/appleID/"
    },
    {
      "account": "ri***@looklooklook.us",
      "email": "richardhamilton1127@looklooklook.us",
      "fullEmail": "richardhamilton1127@looklooklook.us",
      "password": "f7CXDFWHMc",
      "region": "US",
      "regionName": "美国",
      "status": "正常",
      "checkTime": "2026-04-17 23:08:59",
      "crawl_time": "2026-04-17 23:08:59",
      "source_page": "https://ccbaohe.com/appleID/"
    },
    {
      "account": "cl***@looklooklook.us",
      "email": "claudiamartinez0325@looklooklook.us",
      "fullEmail": "claudiamartinez0325@looklooklook.us",
      "password": "8jSBxMHbUw",
      "region": "US",
      "regionName": "美国",
      "status": "正常",
      "checkTime": "2026-04-17 23:08:59",
      "crawl_time": "2026-04-17 23:08:59",
      "source_page": "https://ccbaohe.com/appleID/"
    },
    {
      "account": "mr***@icloud.com",
      "email": "mriryybpw3ytmenpdgnw@icloud.com",
      "fullEmail": "mriryybpw3ytmenpdgnw@icloud.com",
      "password": "YqB6vrSHGq",
      "region": "US",
      "regionName": "美国",
      "status": "正常",
      "checkTime": "2026-04-17 23:08:59",
      "crawl_time": "2026-04-17 23:08:59",
      "source_page": "https://ccbaohe.com/appleID/"
    },
    {
      "account": "fi***@icloud.com",
      "email": "fi6ef2rrocwi4aejm0ei@icloud.com",
      "fullEmail": "fi6ef2rrocwi4aejm0ei@icloud.com",
      "password": "SzSBmezX66",
      "region": "US",
      "regionName": "美国",
      "status": "正常",
      "checkTime": "2026-04-17 23:08:59",
      "crawl_time": "2026-04-17 23:08:59",
      "source_page": "https://ccbaohe.com/appleID/"
    },
    {
      "account": "zd***@icloud.com",
      "email": "zd033zjzodhcgn6h0d@icloud.com",
      "fullEmail": "zd033zjzodhcgn6h0d@icloud.com",
      "password": "SsuaHE8D8a",
      "region": "US",
      "regionName": "美国",
      "status": "正常",
      "checkTime": "2026-04-17 23:08:59",
      "crawl_time": "2026-04-17 23:08:59",
      "source_page": "https://ccbaohe.com/appleID/"
    },
    {
      "account": "nb***@hotmail.com",
      "email": "nbrvc11222@hotmail.com",
      "fullEmail": "nbrvc11222@hotmail.com",
      "password": "RVdE5JjDWs",
      "region": "US",
      "regionName": "美国",
      "status": "正常",
      "checkTime": "2026-04-17 23:08:59",
      "crawl_time": "2026-04-17 23:08:59",
      "source_page": "https://ccbaohe.com/appleID/"
    },
    {
      "account": "dp***@hotmail.com",
      "email": "dpkjknd45561@hotmail.com",
      "fullEmail": "dpkjknd45561@hotmail.com",
      "password": "UnM6JFrANs",
      "region": "US",
      "regionName": "美国",
      "status": "正常",
      "checkTime": "2026-04-17 23:08:59",
      "crawl_time": "2026-04-17 23:08:59",
      "source_page": "https://ccbaohe.com/appleID/"
    },
    {
      "account": "sh***@hotmail.com",
      "email": "sheznjbvd@hotmail.com",
      "fullEmail": "sheznjbvd@hotmail.com",
      "password": "TDafCMC4GkYv",
      "region": "US",
      "regionName": "美国",
      "status": "正常",
      "checkTime": "2026-04-17 23:08:59",
      "crawl_time": "2026-04-17 23:08:59",
      "source_page": "https://ccbaohe.com/appleID/"
    },
    {
      "account": "ju***@hotmail.com",
      "email": "juflgcjql@hotmail.com",
      "fullEmail": "juflgcjql@hotmail.com",
      "password": "TDq55grDa8xF",
      "region": "US",
      "regionName": "美国",
      "status": "正常",
      "checkTime": "2026-04-17 23:08:59",
      "crawl_time": "2026-04-17 23:08:59",
      "source_page": "https://ccbaohe.com/appleID/"
    },
    {
      "account": "im***@hotmail.com",
      "email": "imwnoycjh@hotmail.com",
      "fullEmail": "imwnoycjh@hotmail.com",
      "password": "TDE2ZkC547fu",
      "region": "US",
      "regionName": "美国",
      "status": "正常",
      "checkTime": "2026-04-17 23:08:59",
      "crawl_time": "2026-04-17 23:08:59",
      "source_page": "https://ccbaohe.com/appleID/"
    },
    {
      "account": "cz***@hotmail.com",
      "email": "czbjilstncu@hotmail.com",
      "fullEmail": "czbjilstncu@hotmail.com",
      "password": "TDR1T7zWnfXT",
      "region": "US",
      "regionName": "设置",
      "status": "正常",
      "checkTime": "2026-04-17 23:08:59",
      "crawl_time": "2026-04-17 23:08:59",
      "source_page": "https://ccbaohe.com/appleID/"
    },
    {
      "account": "ii***@hotmail.com",
      "email": "iijluqbfkeek@hotmail.com",
      "fullEmail": "iijluqbfkeek@hotmail.com",
      "password": "TDEc8D5KqCZN",
      "region": "CN",
      "regionName": "中国大陆",
      "status": "正常",
      "checkTime": "2026-04-17 23:08:59",
      "crawl_time": "2026-04-17 23:08:59",
      "source_page": "https://ccbaohe.com/appleID/"
    },
    {
      "account": "rg***@hotmail.com",
      "email": "rgkppwnoi@hotmail.com",
      "fullEmail": "rgkppwnoi@hotmail.com",
      "password": "TD4qzbc2nMFt",
      "region": "US",
      "regionName": "美国",
      "status": "正常",
      "checkTime": "2026-04-17 23:08:59",
      "crawl_time": "2026-04-17 23:08:59",
      "source_page": "https://ccbaohe.com/appleID/"
    },
    {
      "account": "pz***@hotmail.com",
      "email": "pztiyijliya@hotmail.com",
      "fullEmail": "pztiyijliya@hotmail.com",
      "password": "TDBDpxZwAdH5",
      "region": "US",
      "regionName": "美国",
      "status": "正常",
      "checkTime": "2026-04-17 23:08:59",
      "crawl_time": "2026-04-17 23:08:59",
      "source_page": "https://ccbaohe.com/appleID/"
    },
    {
      "account": "qs***@hotmail.com",
      "email": "qsvfcnbhxdk@hotmail.com",
      "fullEmail": "qsvfcnbhxdk@hotmail.com",
      "password": "TDq3ffGwgjNd",
      "region": "US",
      "regionName": "美国",
      "status": "正常",
      "checkTime": "2026-04-17 23:08:59",
      "crawl_time": "2026-04-17 23:08:59",
      "source_page": "https://ccbaohe.com/appleID/"
    },
    {
      "account": "vl***@hotmail.com",
      "email": "vlsxjriqmgywp@hotmail.com",
      "fullEmail": "vlsxjriqmgywp@hotmail.com",
      "password": "TD6VP6CW2hsz",
      "region": "US",
      "regionName": "美国",
      "status": "正常",
      "checkTime": "2026-04-17 23:08:59",
      "crawl_time": "2026-04-17 23:08:59",
      "source_page": "https://ccbaohe.com/appleID/"
    }
  ]
}