[
  {
    "email": "youyudenailao@163.com",
    "password": "xcX4Vj2KNt",
    "region": "US"
  },
  {
    "email": "JoshuaShort2757@hotmail.com",
    "password": "mk9qu3X3Jj",
    "region": "VN"
  },
  {
    "email": "MarissaSnyder4380@outlook.com",
    "password": "5YyPJ3TBSR",
    "region": "JP"
  },
  {
    "email": "dfbrk0@outlook.com",
    "password": "ptcZjAyK8q",
    "region": "US"
  },
  {
    "email": "RyaAlonzo1762@outlook.com",
    "password": "TBdJWeE5m1",
    "region": "US"
  },
  {
    "email": "tbpbvx5@outlook.com",
    "password": "sbp2adPTEY",
    "region": "US"
  },
  {
    "email": "tflnps820@outlook.com",
    "password": "4aAzXHxhar",
    "region": "US"
  },
  {
    "email": "ieqrtpo4@outlook.com",
    "password": "Rttgfn5xK6",
    "region": "US"
  },
  {
    "email": "ppzbimq53@outlook.com",
    "password": "6a4hFKxh6p",
    "region": "US"
  },
  {
    "email": "zvauxns0@outlook.com",
    "password": "FnPP6kd7M7",
    "region": "US"
  },
  {
    "email": "xvjgxh14@outlook.com",
    "password": "ZG1Kd5rW2x",
    "region": "US"
  },
  {
    "email": "joshuawilliamsyk@outlook.co.id",
    "password": "1Q3GA1rd8F",
    "region": "TW"
  },
  {
    "email": "rqzwtz77@outlook.com",
    "password": "92SkfP6Ch8",
    "region": "US"
  },
  {
    "email": "meyd1734@hhl123.club",
    "password": "5umyP3fvXj",
    "region": "CN"
  },
  {
    "email": "njyy1057@hhl123.club",
    "password": "yu3M68UWj4",
    "region": "HK"
  },
  {
    "email": "itfime70@outlook.com",
    "password": "ksF1eG3Txz",
    "region": "US"
  },
  {
    "email": "AllenMilliepyl879@gmail.com",
    "password": "44s41NP3MD5pf3",
    "region": "US"
  },
  {
    "email": "reneq898@outlook.com",
    "password": "gzFaN3Vwqr",
    "region": "US"
  },
  {
    "email": "quodonnell@gmail.com",
    "password": "Dd10096da",
    "region": "US"
  },
  {
    "email": "DeborazpiHarr967@icloud.com",
    "password": "x5Qt9ch9m9",
    "region": "US"
  },
  {
    "email": "jarvarisrivetteuf3409@gmail.com",
    "password": "VG7j2eeg4C",
    "region": "US"
  },
  {
    "email": "BettyGarcia5be56@gmail.com",
    "password": "44s4nrRa3yZnJ5",
    "region": "US"
  },
  {
    "email": "gzhc1838@hhl123.club",
    "password": "kDjkSjKxw4",
    "region": "CN"
  },
  {
    "email": "ehvi1252@hhl123.club",
    "password": "tD668JtaQV",
    "region": "CN"
  },
  {
    "email": "ogre1000@hhl123.club",
    "password": "ZXyVc5Dn2w",
    "region": "US"
  },
  {
    "email": "marioslopes066@hotmail.com",
    "password": "t764qh57Nn",
    "region": "KR"
  },
  {
    "email": "lettyallegra8230@hotmail.com",
    "password": "uqhqy7FD2J",
    "region": "US"
  },
  {
    "email": "briannunezuj@outlook.co.id",
    "password": "Whyx8QvPHJ",
    "region": "HK"
  },
  {
    "email": "vladimirprewitt200@gmail.com",
    "password": "H1QKrpyNgg",
    "region": "KR"
  },
  {
    "email": "aidenuapj@outlook.com",
    "password": "EBWjxcUMt9",
    "region": "US"
  },
  {
    "email": "michaelcar1k@hotmail.com",
    "password": "2Qv72WTNGm",
    "region": "US"
  },
  {
    "email": "logan472gu@outlook.com",
    "password": "jRY7bun6cZ",
    "region": "US"
  },
  {
    "email": "sbdppd378@outlook.com",
    "password": "FBuwJE1PNS",
    "region": "US"
  },
  {
    "email": "Fwpdn89407@outlook.com",
    "password": "Gcu4QkVWk8",
    "region": "US"
  },
  {
    "email": "ihwyqd1@outlook.com",
    "password": "sjEJMu8nxY",
    "region": "US"
  },
  {
    "email": "miraj.ali@hotmail.co.uk",
    "password": "KZcK311fzN",
    "region": "VN"
  },
  {
    "email": "Ypztr96446@outlook.com",
    "password": "x6w1h5JYXu",
    "region": "US"
  },
  {
    "email": "cklnj77@outlook.com",
    "password": "mCQxy5hwVU",
    "region": "US"
  },
  {
    "email": "ulzgwfg79@outlook.com",
    "password": "qpy5jzNGqu",
    "region": "US"
  },
  {
    "email": "rzs561942@outlook.com",
    "password": "wfBw7c9KNf",
    "region": "US"
  },
  {
    "email": "jnjhtrr30@outlook.com",
    "password": "TsQkY8MAk5",
    "region": "US"
  },
  {
    "email": "lgdskwk57@outlook.com",
    "password": "h2k5c9UaS2",
    "region": "US"
  },
  {
    "email": "vmsgkt72@outlook.com",
    "password": "WV6CNMadcM",
    "region": "US"
  },
  {
    "email": "profipiro@freemail.hu",
    "password": "AEP443cBdm",
    "region": "VN"
  },
  {
    "email": "cvankm752@outlook.com",
    "password": "KgeWK8mCGg",
    "region": "US"
  },
  {
    "email": "wanses1@outlook.com",
    "password": "KfjaTX23eT",
    "region": "CN"
  },
  {
    "email": "gvvrey9@outlook.com",
    "password": "6f5tcRf3xk",
    "region": "US"
  }
]