{
  "total": 35,
  "update_time": "2026-05-20 19:11:37",
  "source_url": "https://tkbaohe.com/Shadowrocket/",
  "source_urls": [
    "https://tkbaohe.com/Shadowrocket/",
    "https://ccbaohe.com/appleID/"
  ],
  "accounts": [
    {
      "account": "sh***@i.softbank.jp",
      "email": "shabi0204@i.softbank.jp",
      "fullEmail": "shabi0204@i.softbank.jp",
      "password": "JWAh6Zd7hG",
      "region": "US",
      "regionName": "美国",
      "status": "正常",
      "checkTime": "2026-05-20 19:11:32",
      "crawl_time": "2026-05-20 19:11:32",
      "source_page": "https://tkbaohe.com/Shadowrocket/"
    },
    {
      "account": "qu***@gmail.com",
      "email": "quodonnell@gmail.com",
      "fullEmail": "quodonnell@gmail.com",
      "password": "Dd10096da",
      "region": "US",
      "regionName": "美区",
      "status": "正常",
      "checkTime": "2026-05-20 19:11:32",
      "crawl_time": "2026-05-20 19:11:32",
      "source_page": "https://tkbaohe.com/Shadowrocket/"
    },
    {
      "account": "De***@icloud.com",
      "email": "DeborazpiHarr967@icloud.com",
      "fullEmail": "DeborazpiHarr967@icloud.com",
      "password": "x5Qt9ch9m9",
      "region": "US",
      "regionName": "美区",
      "status": "正常",
      "checkTime": "2026-05-20 19:11:32",
      "crawl_time": "2026-05-20 19:11:32",
      "source_page": "https://tkbaohe.com/Shadowrocket/"
    },
    {
      "account": "ja***@gmail.com",
      "email": "jarvarisrivetteuf3409@gmail.com",
      "fullEmail": "jarvarisrivetteuf3409@gmail.com",
      "password": "VG7j2eeg4C",
      "region": "US",
      "regionName": "美区",
      "status": "正常",
      "checkTime": "2026-05-20 19:11:32",
      "crawl_time": "2026-05-20 19:11:32",
      "source_page": "https://tkbaohe.com/Shadowrocket/"
    },
    {
      "account": "Al***@gmail.com",
      "email": "AllenMilliepyl879@gmail.com",
      "fullEmail": "AllenMilliepyl879@gmail.com",
      "password": "44s41NP3MD5pf3",
      "region": "US",
      "regionName": "美区",
      "status": "正常",
      "checkTime": "2026-05-20 19:11:32",
      "crawl_time": "2026-05-20 19:11:32",
      "source_page": "https://tkbaohe.com/Shadowrocket/"
    },
    {
      "account": "Be***@gmail.com",
      "email": "BettyGarcia5be56@gmail.com",
      "fullEmail": "BettyGarcia5be56@gmail.com",
      "password": "44s4nrRa3yZnJ5",
      "region": "US",
      "regionName": "美区",
      "status": "正常",
      "checkTime": "2026-05-20 19:11:32",
      "crawl_time": "2026-05-20 19:11:32",
      "source_page": "https://tkbaohe.com/Shadowrocket/"
    },
    {
      "account": "mc***@hotmail.com",
      "email": "mchgth05563l@hotmail.com",
      "fullEmail": "mchgth05563l@hotmail.com",
      "password": "qgEEX7rcqD",
      "region": "US",
      "regionName": "美国-🇺",
      "status": "正常",
      "checkTime": "2026-05-20 19:11:32",
      "crawl_time": "2026-05-20 19:11:32",
      "source_page": "https://tkbaohe.com/Shadowrocket/"
    },
    {
      "account": "oi***@hotmail.com",
      "email": "oizfqc04460e@hotmail.com",
      "fullEmail": "oizfqc04460e@hotmail.com",
      "password": "csEVEerq5n",
      "region": "US",
      "regionName": "美国-🇺",
      "status": "正常",
      "checkTime": "2026-05-20 19:11:32",
      "crawl_time": "2026-05-20 19:11:32",
      "source_page": "https://tkbaohe.com/Shadowrocket/"
    },
    {
      "account": "gd***@hotmail.com",
      "email": "gdnack96650r@hotmail.com",
      "fullEmail": "gdnack96650r@hotmail.com",
      "password": "GeGu9s5zR4",
      "region": "US",
      "regionName": "美国-🇺",
      "status": "正常",
      "checkTime": "2026-05-20 19:11:32",
      "crawl_time": "2026-05-20 19:11:32",
      "source_page": "https://tkbaohe.com/Shadowrocket/"
    },
    {
      "account": "ad***@hotmail.com",
      "email": "advqpj82092w@hotmail.com",
      "fullEmail": "advqpj82092w@hotmail.com",
      "password": "UHVqgPPF4D",
      "region": "US",
      "regionName": "美国-🇺",
      "status": "正常",
      "checkTime": "2026-05-20 19:11:32",
      "crawl_time": "2026-05-20 19:11:32",
      "source_page": "https://tkbaohe.com/Shadowrocket/"
    },
    {
      "account": "wq***@hotmail.com",
      "email": "wqdidr18695s@hotmail.com",
      "fullEmail": "wqdidr18695s@hotmail.com",
      "password": "vs5TeNRgpn",
      "region": "US",
      "regionName": "美国-🇺",
      "status": "正常",
      "checkTime": "2026-05-20 19:11:32",
      "crawl_time": "2026-05-20 19:11:32",
      "source_page": "https://tkbaohe.com/Shadowrocket/"
    },
    {
      "account": "ya***@126.com",
      "email": "yangchui198387@126.com",
      "fullEmail": "yangchui198387@126.com",
      "password": "vfwsU9Hbtg",
      "region": "US",
      "regionName": "美区小火箭ID",
      "status": "正常",
      "checkTime": "2026-05-20 19:11:37",
      "crawl_time": "2026-05-20 19:11:37",
      "source_page": "https://ccbaohe.com/appleID/"
    },
    {
      "account": "ke***@icloud.com",
      "email": "ke256t5bir054225@icloud.com",
      "fullEmail": "ke256t5bir054225@icloud.com",
      "password": "5Tb736tvSS",
      "region": "US",
      "regionName": "美国",
      "status": "正常",
      "checkTime": "2026-05-20 19:11:37",
      "crawl_time": "2026-05-20 19:11:37",
      "source_page": "https://ccbaohe.com/appleID/"
    },
    {
      "account": "Tt***@icloud.com",
      "email": "TtinaCbasey42502@icloud.com",
      "fullEmail": "TtinaCbasey42502@icloud.com",
      "password": "Tv8kYddETS",
      "region": "US",
      "regionName": "美国",
      "status": "正常",
      "checkTime": "2026-05-20 19:11:37",
      "crawl_time": "2026-05-20 19:11:37",
      "source_page": "https://ccbaohe.com/appleID/"
    },
    {
      "account": "em***@dublin.com",
      "email": "emma435@dublin.com",
      "fullEmail": "emma435@dublin.com",
      "password": "wQr1yTWgHH",
      "region": "US",
      "regionName": "美国",
      "status": "正常",
      "checkTime": "2026-05-20 19:11:37",
      "crawl_time": "2026-05-20 19:11:37",
      "source_page": "https://ccbaohe.com/appleID/"
    },
    {
      "account": "ca***@icloud.com",
      "email": "carter15apuhsq533929@icloud.com",
      "fullEmail": "carter15apuhsq533929@icloud.com",
      "password": "UBSH923Gu1",
      "region": "US",
      "regionName": "美国",
      "status": "正常",
      "checkTime": "2026-05-20 19:11:37",
      "crawl_time": "2026-05-20 19:11:37",
      "source_page": "https://ccbaohe.com/appleID/"
    },
    {
      "account": "hu***@icloud.com",
      "email": "hudson15iu5v5v823823@icloud.com",
      "fullEmail": "hudson15iu5v5v823823@icloud.com",
      "password": "5g6WgRuPqg",
      "region": "US",
      "regionName": "美国",
      "status": "正常",
      "checkTime": "2026-05-20 19:11:37",
      "crawl_time": "2026-05-20 19:11:37",
      "source_page": "https://ccbaohe.com/appleID/"
    },
    {
      "account": "tu***@icloud.com",
      "email": "turner124urdtj300058@icloud.com",
      "fullEmail": "turner124urdtj300058@icloud.com",
      "password": "2uD65jhyNF",
      "region": "US",
      "regionName": "美国",
      "status": "正常",
      "checkTime": "2026-05-20 19:11:37",
      "crawl_time": "2026-05-20 19:11:37",
      "source_page": "https://ccbaohe.com/appleID/"
    },
    {
      "account": "cc***@icloud.com",
      "email": "cco29mu4qkg474455@icloud.com",
      "fullEmail": "cco29mu4qkg474455@icloud.com",
      "password": "T7U6tStREw",
      "region": "US",
      "regionName": "美国",
      "status": "正常",
      "checkTime": "2026-05-20 19:11:37",
      "crawl_time": "2026-05-20 19:11:37",
      "source_page": "https://ccbaohe.com/appleID/"
    },
    {
      "account": "yi***@outlook.com",
      "email": "yilvcsfuxybu@outlook.com",
      "fullEmail": "yilvcsfuxybu@outlook.com",
      "password": "XXs4GJJ8j1",
      "region": "US",
      "regionName": "美国",
      "status": "正常",
      "checkTime": "2026-05-20 19:11:37",
      "crawl_time": "2026-05-20 19:11:37",
      "source_page": "https://ccbaohe.com/appleID/"
    },
    {
      "account": "no***@dublin.com",
      "email": "noah820@dublin.com",
      "fullEmail": "noah820@dublin.com",
      "password": "fN5zUBVUKg",
      "region": "US",
      "regionName": "美国",
      "status": "正常",
      "checkTime": "2026-05-20 19:11:37",
      "crawl_time": "2026-05-20 19:11:37",
      "source_page": "https://ccbaohe.com/appleID/"
    },
    {
      "account": "jo***@elvisfan.com",
      "email": "joshua34@elvisfan.com",
      "fullEmail": "joshua34@elvisfan.com",
      "password": "AGmHsP4HqC",
      "region": "US",
      "regionName": "美国",
      "status": "正常",
      "checkTime": "2026-05-20 19:11:37",
      "crawl_time": "2026-05-20 19:11:37",
      "source_page": "https://ccbaohe.com/appleID/"
    },
    {
      "account": "er***@icloud.com",
      "email": "er16fjtgxu177639@icloud.com",
      "fullEmail": "er16fjtgxu177639@icloud.com",
      "password": "z9GrPFhU4q",
      "region": "US",
      "regionName": "美国",
      "status": "正常",
      "checkTime": "2026-05-20 19:11:37",
      "crawl_time": "2026-05-20 19:11:37",
      "source_page": "https://ccbaohe.com/appleID/"
    },
    {
      "account": "no***@elvisfan.com",
      "email": "noah11@elvisfan.com",
      "fullEmail": "noah11@elvisfan.com",
      "password": "TcaXHg8fr9",
      "region": "US",
      "regionName": "美国",
      "status": "正常",
      "checkTime": "2026-05-20 19:11:37",
      "crawl_time": "2026-05-20 19:11:37",
      "source_page": "https://ccbaohe.com/appleID/"
    },
    {
      "account": "er***@icloud.com",
      "email": "er04tjxzgh055375@icloud.com",
      "fullEmail": "er04tjxzgh055375@icloud.com",
      "password": "scAbYr7bAx",
      "region": "US",
      "regionName": "美国",
      "status": "正常",
      "checkTime": "2026-05-20 19:11:37",
      "crawl_time": "2026-05-20 19:11:37",
      "source_page": "https://ccbaohe.com/appleID/"
    },
    {
      "account": "ha***@icloud.com",
      "email": "ha2255vqcp253959@icloud.com",
      "fullEmail": "ha2255vqcp253959@icloud.com",
      "password": "QPuZQej9rG",
      "region": "US",
      "regionName": "美国",
      "status": "正常",
      "checkTime": "2026-05-20 19:11:37",
      "crawl_time": "2026-05-20 19:11:37",
      "source_page": "https://ccbaohe.com/appleID/"
    },
    {
      "account": "ei***@icloud.com",
      "email": "eiser155yzhiw061602@icloud.com",
      "fullEmail": "eiser155yzhiw061602@icloud.com",
      "password": "X3SpnhddAJ",
      "region": "US",
      "regionName": "美国",
      "status": "正常",
      "checkTime": "2026-05-20 19:11:37",
      "crawl_time": "2026-05-20 19:11:37",
      "source_page": "https://ccbaohe.com/appleID/"
    },
    {
      "account": "ol***@elvisfan.com",
      "email": "olivia34@elvisfan.com",
      "fullEmail": "olivia34@elvisfan.com",
      "password": "ZQ5cVghWfE",
      "region": "US",
      "regionName": "美国",
      "status": "正常",
      "checkTime": "2026-05-20 19:11:37",
      "crawl_time": "2026-05-20 19:11:37",
      "source_page": "https://ccbaohe.com/appleID/"
    },
    {
      "account": "em***@dublin.com",
      "email": "emily745@dublin.com",
      "fullEmail": "emily745@dublin.com",
      "password": "Mprwe3yqsv",
      "region": "US",
      "regionName": "美国",
      "status": "正常",
      "checkTime": "2026-05-20 19:11:37",
      "crawl_time": "2026-05-20 19:11:37",
      "source_page": "https://ccbaohe.com/appleID/"
    },
    {
      "account": "en***@icloud.com",
      "email": "enberg09mt3tcw589184@icloud.com",
      "fullEmail": "enberg09mt3tcw589184@icloud.com",
      "password": "nvwHBur4MJ",
      "region": "US",
      "regionName": "美国",
      "status": "正常",
      "checkTime": "2026-05-20 19:11:37",
      "crawl_time": "2026-05-20 19:11:37",
      "source_page": "https://ccbaohe.com/appleID/"
    },
    {
      "account": "br***@icloud.com",
      "email": "bruen01a4x56b470891@icloud.com",
      "fullEmail": "bruen01a4x56b470891@icloud.com",
      "password": "KdFtnt42QU",
      "region": "US",
      "regionName": "美国",
      "status": "正常",
      "checkTime": "2026-05-20 19:11:37",
      "crawl_time": "2026-05-20 19:11:37",
      "source_page": "https://ccbaohe.com/appleID/"
    },
    {
      "account": "ab***@dublin.com",
      "email": "abigail551@dublin.com",
      "fullEmail": "abigail551@dublin.com",
      "password": "rAe1jmCPVe",
      "region": "US",
      "regionName": "美国",
      "status": "正常",
      "checkTime": "2026-05-20 19:11:37",
      "crawl_time": "2026-05-20 19:11:37",
      "source_page": "https://ccbaohe.com/appleID/"
    },
    {
      "account": "da***@dublin.com",
      "email": "daniel761@dublin.com",
      "fullEmail": "daniel761@dublin.com",
      "password": "3qAD1Nwrc9",
      "region": "US",
      "regionName": "美国",
      "status": "正常",
      "checkTime": "2026-05-20 19:11:37",
      "crawl_time": "2026-05-20 19:11:37",
      "source_page": "https://ccbaohe.com/appleID/"
    },
    {
      "account": "jo***@elvisfan.com",
      "email": "john45@elvisfan.com",
      "fullEmail": "john45@elvisfan.com",
      "password": "N5RDTkRXXm",
      "region": "US",
      "regionName": "美国",
      "status": "正常",
      "checkTime": "2026-05-20 19:11:37",
      "crawl_time": "2026-05-20 19:11:37",
      "source_page": "https://ccbaohe.com/appleID/"
    },
    {
      "account": "ng***@icloud.com",
      "email": "ngibdlz588522@icloud.com",
      "fullEmail": "ngibdlz588522@icloud.com",
      "password": "JssAWq1G",
      "region": "US",
      "regionName": "美国",
      "status": "正常",
      "checkTime": "2026-05-20 19:11:37",
      "crawl_time": "2026-05-20 19:11:37",
      "source_page": "https://ccbaohe.com/appleID/"
    }
  ]
}