{
  "total": 44,
  "update_time": "2026-05-04 22:45:41",
  "source_url": "https://tkbaohe.com/Shadowrocket/",
  "source_urls": [
    "https://tkbaohe.com/Shadowrocket/",
    "https://ccbaohe.com/appleID/"
  ],
  "accounts": [
    {
      "account": "Wi***@outlook.com",
      "email": "WildeHarriet1992@outlook.com",
      "fullEmail": "WildeHarriet1992@outlook.com",
      "password": "jgPmf11wze",
      "region": "US",
      "regionName": "美国-🇺",
      "status": "正常",
      "checkTime": "2026-05-04 22:45:38",
      "crawl_time": "2026-05-04 22:45:38",
      "source_page": "https://tkbaohe.com/Shadowrocket/"
    },
    {
      "account": "l4***@hotmail.com",
      "email": "l4X1pJ36mMb@hotmail.com",
      "fullEmail": "l4X1pJ36mMb@hotmail.com",
      "password": "R42EN12n7w",
      "region": "US",
      "regionName": "美国-🇺",
      "status": "正常",
      "checkTime": "2026-05-04 22:45:38",
      "crawl_time": "2026-05-04 22:45:38",
      "source_page": "https://tkbaohe.com/Shadowrocket/"
    },
    {
      "account": "js***@outlook.com",
      "email": "jsgsn45996976@outlook.com",
      "fullEmail": "jsgsn45996976@outlook.com",
      "password": "hm6KqKvY7K",
      "region": "US",
      "regionName": "美区小火箭ID",
      "status": "正常",
      "checkTime": "2026-05-04 22:45:38",
      "crawl_time": "2026-05-04 22:45:38",
      "source_page": "https://tkbaohe.com/Shadowrocket/"
    },
    {
      "account": "nl***@outlook.com",
      "email": "nljhs17072228@outlook.com",
      "fullEmail": "nljhs17072228@outlook.com",
      "password": "BtXg62CGbs",
      "region": "US",
      "regionName": "美区小火箭ID",
      "status": "正常",
      "checkTime": "2026-05-04 22:45:38",
      "crawl_time": "2026-05-04 22:45:38",
      "source_page": "https://tkbaohe.com/Shadowrocket/"
    },
    {
      "account": "ri***@outlook.com",
      "email": "rijtt83250635@outlook.com",
      "fullEmail": "rijtt83250635@outlook.com",
      "password": "F5NneEd8SM",
      "region": "US",
      "regionName": "美区小火箭ID",
      "status": "正常",
      "checkTime": "2026-05-04 22:45:38",
      "crawl_time": "2026-05-04 22:45:38",
      "source_page": "https://tkbaohe.com/Shadowrocket/"
    },
    {
      "account": "vo***@outlook.com",
      "email": "vobcj93358879@outlook.com",
      "fullEmail": "vobcj93358879@outlook.com",
      "password": "P8VdP3Ngb8",
      "region": "US",
      "regionName": "美区小火箭ID",
      "status": "正常",
      "checkTime": "2026-05-04 22:45:38",
      "crawl_time": "2026-05-04 22:45:38",
      "source_page": "https://tkbaohe.com/Shadowrocket/"
    },
    {
      "account": "ma***@hotmail.com",
      "email": "makortchiyaf@hotmail.com",
      "fullEmail": "makortchiyaf@hotmail.com",
      "password": "y514sVsq25",
      "region": "US",
      "regionName": "日本-🇯🇵",
      "status": "正常",
      "checkTime": "2026-05-04 22:45:38",
      "crawl_time": "2026-05-04 22:45:38",
      "source_page": "https://tkbaohe.com/Shadowrocket/"
    },
    {
      "account": "mo***@hotmail.com",
      "email": "mosbruckervanarsdale01@hotmail.com",
      "fullEmail": "mosbruckervanarsdale01@hotmail.com",
      "password": "hRQ8Hn7yjq",
      "region": "US",
      "regionName": "香港-🇨🇳",
      "status": "正常",
      "checkTime": "2026-05-04 22:45:38",
      "crawl_time": "2026-05-04 22:45:38",
      "source_page": "https://tkbaohe.com/Shadowrocket/"
    },
    {
      "account": "ri***@icloud.com",
      "email": "richardalholland1u8@icloud.com",
      "fullEmail": "richardalholland1u8@icloud.com",
      "password": "h2GeXwQTUg",
      "region": "US",
      "regionName": "韩国-🇰🇷",
      "status": "正常",
      "checkTime": "2026-05-04 22:45:38",
      "crawl_time": "2026-05-04 22:45:38",
      "source_page": "https://tkbaohe.com/Shadowrocket/"
    },
    {
      "account": "Na***@hotmail.com",
      "email": "NathanieiJonas1967@hotmail.com",
      "fullEmail": "NathanieiJonas1967@hotmail.com",
      "password": "TS6XHryPgT",
      "region": "US",
      "regionName": "美区小火箭ID",
      "status": "正常",
      "checkTime": "2026-05-04 22:45:38",
      "crawl_time": "2026-05-04 22:45:38",
      "source_page": "https://tkbaohe.com/Shadowrocket/"
    },
    {
      "account": "vf***@outlook.com",
      "email": "vfwci10353668@outlook.com",
      "fullEmail": "vfwci10353668@outlook.com",
      "password": "p7pkVWsEUY",
      "region": "US",
      "regionName": "美区小火箭ID",
      "status": "正常",
      "checkTime": "2026-05-04 22:45:41",
      "crawl_time": "2026-05-04 22:45:41",
      "source_page": "https://ccbaohe.com/appleID/"
    },
    {
      "account": "dg***@outlook.com",
      "email": "dgsyd54365658@outlook.com",
      "fullEmail": "dgsyd54365658@outlook.com",
      "password": "JTwu2GtqpN",
      "region": "US",
      "regionName": "美区小火箭ID",
      "status": "正常",
      "checkTime": "2026-05-04 22:45:41",
      "crawl_time": "2026-05-04 22:45:41",
      "source_page": "https://ccbaohe.com/appleID/"
    },
    {
      "account": "wd***@outlook.com",
      "email": "wdkfp39388420@outlook.com",
      "fullEmail": "wdkfp39388420@outlook.com",
      "password": "TpFgas7zPd",
      "region": "US",
      "regionName": "美区小火箭ID",
      "status": "正常",
      "checkTime": "2026-05-04 22:45:41",
      "crawl_time": "2026-05-04 22:45:41",
      "source_page": "https://ccbaohe.com/appleID/"
    },
    {
      "account": "pz***@outlook.com",
      "email": "pzxqu28387646@outlook.com",
      "fullEmail": "pzxqu28387646@outlook.com",
      "password": "ab9eVFHGhb",
      "region": "US",
      "regionName": "美区小火箭ID",
      "status": "正常",
      "checkTime": "2026-05-04 22:45:41",
      "crawl_time": "2026-05-04 22:45:41",
      "source_page": "https://ccbaohe.com/appleID/"
    },
    {
      "account": "ia***@outlook.com",
      "email": "iajey61152556@outlook.com",
      "fullEmail": "iajey61152556@outlook.com",
      "password": "sM16nambXE",
      "region": "US",
      "regionName": "美区小火箭ID",
      "status": "正常",
      "checkTime": "2026-05-04 22:45:41",
      "crawl_time": "2026-05-04 22:45:41",
      "source_page": "https://ccbaohe.com/appleID/"
    },
    {
      "account": "ma***@hotmail.com",
      "email": "manumitcaracolebiammg@hotmail.com",
      "fullEmail": "manumitcaracolebiammg@hotmail.com",
      "password": "Xy7tAFc3Qn",
      "region": "CN",
      "regionName": "中国大陆",
      "status": "正常",
      "checkTime": "2026-05-04 22:45:41",
      "crawl_time": "2026-05-04 22:45:41",
      "source_page": "https://ccbaohe.com/appleID/"
    },
    {
      "account": "sh***@hotmail.com",
      "email": "shohamasak5926@hotmail.com",
      "fullEmail": "shohamasak5926@hotmail.com",
      "password": "mNYew8agRQ",
      "region": "VN",
      "regionName": "越南",
      "status": "正常",
      "checkTime": "2026-05-04 22:45:41",
      "crawl_time": "2026-05-04 22:45:41",
      "source_page": "https://ccbaohe.com/appleID/"
    },
    {
      "account": "ke***@outlook.com.br",
      "email": "kevinschroedertt2232@outlook.com.br",
      "fullEmail": "kevinschroedertt2232@outlook.com.br",
      "password": "MgH7t49TK7",
      "region": "CN",
      "regionName": "中国大陆",
      "status": "正常",
      "checkTime": "2026-05-04 22:45:41",
      "crawl_time": "2026-05-04 22:45:41",
      "source_page": "https://ccbaohe.com/appleID/"
    },
    {
      "account": "ro***@outlook.com",
      "email": "rowgahopvcliev@outlook.com",
      "fullEmail": "rowgahopvcliev@outlook.com",
      "password": "HpQ6rWmffS",
      "region": "US",
      "regionName": "美国",
      "status": "正常",
      "checkTime": "2026-05-04 22:45:41",
      "crawl_time": "2026-05-04 22:45:41",
      "source_page": "https://ccbaohe.com/appleID/"
    },
    {
      "account": "Ga***@hotmail.com",
      "email": "GalbraithStanley1996@hotmail.com",
      "fullEmail": "GalbraithStanley1996@hotmail.com",
      "password": "w7y1eyDr3t",
      "region": "US",
      "regionName": "美国",
      "status": "正常",
      "checkTime": "2026-05-04 22:45:41",
      "crawl_time": "2026-05-04 22:45:41",
      "source_page": "https://ccbaohe.com/appleID/"
    },
    {
      "account": "xk***@outlook.com",
      "email": "xkyieewu@outlook.com",
      "fullEmail": "xkyieewu@outlook.com",
      "password": "MK5Gav3PSh",
      "region": "US",
      "regionName": "美国",
      "status": "正常",
      "checkTime": "2026-05-04 22:45:41",
      "crawl_time": "2026-05-04 22:45:41",
      "source_page": "https://ccbaohe.com/appleID/"
    },
    {
      "account": "kx***@outlook.com",
      "email": "kxjjuarfcmeh@outlook.com",
      "fullEmail": "kxjjuarfcmeh@outlook.com",
      "password": "gbGQm46vaU",
      "region": "US",
      "regionName": "美国",
      "status": "正常",
      "checkTime": "2026-05-04 22:45:41",
      "crawl_time": "2026-05-04 22:45:41",
      "source_page": "https://ccbaohe.com/appleID/"
    },
    {
      "account": "rl***@outlook.com",
      "email": "rlqnkzcwrdvspo@outlook.com",
      "fullEmail": "rlqnkzcwrdvspo@outlook.com",
      "password": "gq3DqwYdmk",
      "region": "US",
      "regionName": "美国",
      "status": "正常",
      "checkTime": "2026-05-04 22:45:41",
      "crawl_time": "2026-05-04 22:45:41",
      "source_page": "https://ccbaohe.com/appleID/"
    },
    {
      "account": "ue***@outlook.com",
      "email": "ueholoekp@outlook.com",
      "fullEmail": "ueholoekp@outlook.com",
      "password": "2FApFD9qzP",
      "region": "US",
      "regionName": "美国",
      "status": "正常",
      "checkTime": "2026-05-04 22:45:41",
      "crawl_time": "2026-05-04 22:45:41",
      "source_page": "https://ccbaohe.com/appleID/"
    },
    {
      "account": "mq***@outlook.com",
      "email": "mqpypmion@outlook.com",
      "fullEmail": "mqpypmion@outlook.com",
      "password": "Gjr5EzdqN9",
      "region": "US",
      "regionName": "美国",
      "status": "正常",
      "checkTime": "2026-05-04 22:45:41",
      "crawl_time": "2026-05-04 22:45:41",
      "source_page": "https://ccbaohe.com/appleID/"
    },
    {
      "account": "cj***@outlook.com",
      "email": "cjzdxujuv@outlook.com",
      "fullEmail": "cjzdxujuv@outlook.com",
      "password": "yQJpF1CKv7",
      "region": "US",
      "regionName": "美国",
      "status": "正常",
      "checkTime": "2026-05-04 22:45:41",
      "crawl_time": "2026-05-04 22:45:41",
      "source_page": "https://ccbaohe.com/appleID/"
    },
    {
      "account": "jk***@outlook.com",
      "email": "jkxdqepg@outlook.com",
      "fullEmail": "jkxdqepg@outlook.com",
      "password": "xygE4a6UeD",
      "region": "US",
      "regionName": "美国",
      "status": "正常",
      "checkTime": "2026-05-04 22:45:41",
      "crawl_time": "2026-05-04 22:45:41",
      "source_page": "https://ccbaohe.com/appleID/"
    },
    {
      "account": "dy***@outlook.com",
      "email": "dyoxoqzvh@outlook.com",
      "fullEmail": "dyoxoqzvh@outlook.com",
      "password": "xr7zUY235y",
      "region": "US",
      "regionName": "美国",
      "status": "正常",
      "checkTime": "2026-05-04 22:45:41",
      "crawl_time": "2026-05-04 22:45:41",
      "source_page": "https://ccbaohe.com/appleID/"
    },
    {
      "account": "dk***@outlook.com",
      "email": "dkgbcpylh@outlook.com",
      "fullEmail": "dkgbcpylh@outlook.com",
      "password": "hcJrB3ynmK",
      "region": "US",
      "regionName": "美国",
      "status": "正常",
      "checkTime": "2026-05-04 22:45:41",
      "crawl_time": "2026-05-04 22:45:41",
      "source_page": "https://ccbaohe.com/appleID/"
    },
    {
      "account": "pr***@icloud.com",
      "email": "prestonnatchandle1h3@icloud.com",
      "fullEmail": "prestonnatchandle1h3@icloud.com",
      "password": "erd2SjGZry",
      "region": "US",
      "regionName": "美国",
      "status": "正常",
      "checkTime": "2026-05-04 22:45:41",
      "crawl_time": "2026-05-04 22:45:41",
      "source_page": "https://ccbaohe.com/appleID/"
    },
    {
      "account": "ko***@hotmail.com",
      "email": "koqe12575@hotmail.com",
      "fullEmail": "koqe12575@hotmail.com",
      "password": "RDvfvvDGf1",
      "region": "US",
      "regionName": "美国",
      "status": "正常",
      "checkTime": "2026-05-04 22:45:41",
      "crawl_time": "2026-05-04 22:45:41",
      "source_page": "https://ccbaohe.com/appleID/"
    },
    {
      "account": "ya***@outlook.com",
      "email": "yazvozplubgkf@outlook.com",
      "fullEmail": "yazvozplubgkf@outlook.com",
      "password": "ZHFkEqBH8K",
      "region": "US",
      "regionName": "美国",
      "status": "正常",
      "checkTime": "2026-05-04 22:45:41",
      "crawl_time": "2026-05-04 22:45:41",
      "source_page": "https://ccbaohe.com/appleID/"
    },
    {
      "account": "sl***@outlook.com",
      "email": "slldstyyenzzm@outlook.com",
      "fullEmail": "slldstyyenzzm@outlook.com",
      "password": "jYKnSm3VR5",
      "region": "US",
      "regionName": "美国",
      "status": "正常",
      "checkTime": "2026-05-04 22:45:41",
      "crawl_time": "2026-05-04 22:45:41",
      "source_page": "https://ccbaohe.com/appleID/"
    },
    {
      "account": "rl***@outlook.com",
      "email": "rldcphjqvzlof@outlook.com",
      "fullEmail": "rldcphjqvzlof@outlook.com",
      "password": "3ARGpUC31Z",
      "region": "US",
      "regionName": "美国",
      "status": "正常",
      "checkTime": "2026-05-04 22:45:41",
      "crawl_time": "2026-05-04 22:45:41",
      "source_page": "https://ccbaohe.com/appleID/"
    },
    {
      "account": "yj***@outlook.com",
      "email": "yjazsrcpc388504@outlook.com",
      "fullEmail": "yjazsrcpc388504@outlook.com",
      "password": "986J2yHARF",
      "region": "US",
      "regionName": "美国",
      "status": "正常",
      "checkTime": "2026-05-04 22:45:41",
      "crawl_time": "2026-05-04 22:45:41",
      "source_page": "https://ccbaohe.com/appleID/"
    },
    {
      "account": "Me***@outlook.at",
      "email": "MeaganAllen8618@outlook.at",
      "fullEmail": "MeaganAllen8618@outlook.at",
      "password": "FJ262Bx7mr",
      "region": "US",
      "regionName": "美国",
      "status": "正常",
      "checkTime": "2026-05-04 22:45:41",
      "crawl_time": "2026-05-04 22:45:41",
      "source_page": "https://ccbaohe.com/appleID/"
    },
    {
      "account": "xg***@outlook.com",
      "email": "xgiyiuujdzvaix@outlook.com",
      "fullEmail": "xgiyiuujdzvaix@outlook.com",
      "password": "9UxBGw2KRC",
      "region": "US",
      "regionName": "美国",
      "status": "正常",
      "checkTime": "2026-05-04 22:45:41",
      "crawl_time": "2026-05-04 22:45:41",
      "source_page": "https://ccbaohe.com/appleID/"
    },
    {
      "account": "vd***@outlook.com",
      "email": "vdoflwmdm@outlook.com",
      "fullEmail": "vdoflwmdm@outlook.com",
      "password": "2edf8MssNz",
      "region": "US",
      "regionName": "美国",
      "status": "正常",
      "checkTime": "2026-05-04 22:45:41",
      "crawl_time": "2026-05-04 22:45:41",
      "source_page": "https://ccbaohe.com/appleID/"
    },
    {
      "account": "ar***@outlook.com",
      "email": "artanrpvvoio@outlook.com",
      "fullEmail": "artanrpvvoio@outlook.com",
      "password": "xg3Jy5RUgB",
      "region": "US",
      "regionName": "美国",
      "status": "正常",
      "checkTime": "2026-05-04 22:45:41",
      "crawl_time": "2026-05-04 22:45:41",
      "source_page": "https://ccbaohe.com/appleID/"
    },
    {
      "account": "yd***@outlook.com",
      "email": "ydztzdsuguz@outlook.com",
      "fullEmail": "ydztzdsuguz@outlook.com",
      "password": "MayBE9tDmr",
      "region": "US",
      "regionName": "美国",
      "status": "正常",
      "checkTime": "2026-05-04 22:45:41",
      "crawl_time": "2026-05-04 22:45:41",
      "source_page": "https://ccbaohe.com/appleID/"
    },
    {
      "account": "dn***@outlook.com",
      "email": "dnaruzkuohp@outlook.com",
      "fullEmail": "dnaruzkuohp@outlook.com",
      "password": "x9SsuM7BsD",
      "region": "US",
      "regionName": "美国",
      "status": "正常",
      "checkTime": "2026-05-04 22:45:41",
      "crawl_time": "2026-05-04 22:45:41",
      "source_page": "https://ccbaohe.com/appleID/"
    },
    {
      "account": "so***@outlook.com",
      "email": "sozzrevmzqcnt@outlook.com",
      "fullEmail": "sozzrevmzqcnt@outlook.com",
      "password": "Kn19vjHMU3",
      "region": "US",
      "regionName": "美国",
      "status": "正常",
      "checkTime": "2026-05-04 22:45:41",
      "crawl_time": "2026-05-04 22:45:41",
      "source_page": "https://ccbaohe.com/appleID/"
    },
    {
      "account": "uz***@outlook.com",
      "email": "uzzaciep@outlook.com",
      "fullEmail": "uzzaciep@outlook.com",
      "password": "QE8j8Pbzdu",
      "region": "US",
      "regionName": "美国",
      "status": "正常",
      "checkTime": "2026-05-04 22:45:41",
      "crawl_time": "2026-05-04 22:45:41",
      "source_page": "https://ccbaohe.com/appleID/"
    },
    {
      "account": "sh***@outlook.com",
      "email": "shight_maximh@outlook.com",
      "fullEmail": "shight_maximh@outlook.com",
      "password": "Twq86t51",
      "region": "CN",
      "regionName": "中国大陆",
      "status": "正常",
      "checkTime": "2026-05-04 22:45:41",
      "crawl_time": "2026-05-04 22:45:41",
      "source_page": "https://ccbaohe.com/appleID/"
    }
  ]
}