[
  {
    "email": "WildeHarriet1992@outlook.com",
    "password": "jgPmf11wze",
    "region": "US"
  },
  {
    "email": "l4X1pJ36mMb@hotmail.com",
    "password": "R42EN12n7w",
    "region": "US"
  },
  {
    "email": "jsgsn45996976@outlook.com",
    "password": "hm6KqKvY7K",
    "region": "US"
  },
  {
    "email": "nljhs17072228@outlook.com",
    "password": "BtXg62CGbs",
    "region": "US"
  },
  {
    "email": "rijtt83250635@outlook.com",
    "password": "F5NneEd8SM",
    "region": "US"
  },
  {
    "email": "vobcj93358879@outlook.com",
    "password": "P8VdP3Ngb8",
    "region": "US"
  },
  {
    "email": "makortchiyaf@hotmail.com",
    "password": "y514sVsq25",
    "region": "US"
  },
  {
    "email": "mosbruckervanarsdale01@hotmail.com",
    "password": "hRQ8Hn7yjq",
    "region": "US"
  },
  {
    "email": "richardalholland1u8@icloud.com",
    "password": "h2GeXwQTUg",
    "region": "US"
  },
  {
    "email": "NathanieiJonas1967@hotmail.com",
    "password": "TS6XHryPgT",
    "region": "US"
  },
  {
    "email": "dgsyd54365658@outlook.com",
    "password": "Jx4fDeTmca",
    "region": "US"
  },
  {
    "email": "wdkfp39388420@outlook.com",
    "password": "2kE7fv2vem",
    "region": "US"
  },
  {
    "email": "iajey61152556@outlook.com",
    "password": "n1P6megcpF",
    "region": "US"
  },
  {
    "email": "bwvnx06294193@outlook.com",
    "password": "qgmcwuDhJ6",
    "region": "US"
  },
  {
    "email": "vfwci10353668@outlook.com",
    "password": "aSCyUJezK9",
    "region": "US"
  },
  {
    "email": "quela80348981@outlook.com",
    "password": "BPXNwz58WS",
    "region": "US"
  },
  {
    "email": "ricuxxyncgtdcaol@hotmail.com",
    "password": "2fAchhUmp2",
    "region": "KR"
  },
  {
    "email": "manumitcaracolebiammg@hotmail.com",
    "password": "NVJcye6EHb",
    "region": "CN"
  },
  {
    "email": "shohamasak5926@hotmail.com",
    "password": "mNYew8agRQ",
    "region": "VN"
  },
  {
    "email": "GalbraithStanley1996@hotmail.com",
    "password": "w7y1eyDr3t",
    "region": "US"
  },
  {
    "email": "dnaruzkuohp@outlook.com",
    "password": "U8fZGn4Uqu",
    "region": "US"
  },
  {
    "email": "yazvozplubgkf@outlook.com",
    "password": "ZHFkEqBH8K",
    "region": "US"
  },
  {
    "email": "koqe12575@hotmail.com",
    "password": "RDvfvvDGf1",
    "region": "US"
  },
  {
    "email": "sozzrevmzqcnt@outlook.com",
    "password": "Kn19vjHMU3",
    "region": "US"
  },
  {
    "email": "dyoxoqzvh@outlook.com",
    "password": "xr7zUY235y",
    "region": "US"
  },
  {
    "email": "rowgahopvcliev@outlook.com",
    "password": "tdexU6yYRx",
    "region": "US"
  },
  {
    "email": "prestonnatchandle1h3@icloud.com",
    "password": "erd2SjGZry",
    "region": "US"
  },
  {
    "email": "rldcphjqvzlof@outlook.com",
    "password": "eh4vRjfWUn",
    "region": "US"
  },
  {
    "email": "MeaganAllen8618@outlook.at",
    "password": "YeFrBAsSF5",
    "region": "US"
  },
  {
    "email": "slldstyyenzzm@outlook.com",
    "password": "jYKnSm3VR5",
    "region": "US"
  },
  {
    "email": "jkxdqepg@outlook.com",
    "password": "h9dtMPCHKt",
    "region": "US"
  },
  {
    "email": "ydztzdsuguz@outlook.com",
    "password": "MayBE9tDmr",
    "region": "US"
  },
  {
    "email": "rlqnkzcwrdvspo@outlook.com",
    "password": "gq3DqwYdmk",
    "region": "US"
  },
  {
    "email": "mqpypmion@outlook.com",
    "password": "Gjr5EzdqN9",
    "region": "US"
  },
  {
    "email": "ueholoekp@outlook.com",
    "password": "kmGyBB1j8Y",
    "region": "US"
  },
  {
    "email": "yjazsrcpc388504@outlook.com",
    "password": "986J2yHARF",
    "region": "US"
  },
  {
    "email": "kxjjuarfcmeh@outlook.com",
    "password": "rympG2dx83",
    "region": "US"
  },
  {
    "email": "xgiyiuujdzvaix@outlook.com",
    "password": "nXrZwyQ2t9",
    "region": "US"
  },
  {
    "email": "cjzdxujuv@outlook.com",
    "password": "yQJpF1CKv7",
    "region": "US"
  },
  {
    "email": "artanrpvvoio@outlook.com",
    "password": "yxR5xbTcW8",
    "region": "US"
  },
  {
    "email": "uzzaciep@outlook.com",
    "password": "BCJxHARe8P",
    "region": "US"
  },
  {
    "email": "dkgbcpylh@outlook.com",
    "password": "HwQ5Bd7Ntm",
    "region": "US"
  },
  {
    "email": "vdoflwmdm@outlook.com",
    "password": "DgXWWhC7Rt",
    "region": "US"
  },
  {
    "email": "linejdeli90@outlook.com",
    "password": "nk8XXyeA",
    "region": "TW"
  }
]