{
  "update_time": "2026-06-01 14:45:54",
  "count": 2,
  "accounts": [
    {
      "account": "un***@hotmail.com",
      "email": "unqfkv25185g@hotmail.com",
      "fullEmail": "unqfkv25185g@hotmail.com",
      "password": "E9PQexh1Un",
      "region": "US",
      "regionName": "美国",
      "status": "正常",
      "checkTime": "2026-06-01 14:45:54",
      "crawl_time": "2026-06-01 14:45:54",
      "source_page": "https://ccbaohe.com/appleID/"
    },
    {
      "account": "Su***@outlook.com",
      "email": "SusanDiazhdon@outlook.com",
      "fullEmail": "SusanDiazhdon@outlook.com",
      "password": "9Ee5M74ZND",
      "region": "US",
      "regionName": "韩国-🇰🇷",
      "status": "正常",
      "checkTime": "2026-06-01 14:45:51",
      "crawl_time": "2026-06-01 14:45:51",
      "source_page": "https://tkbaohe.com/Shadowrocket/"
    }
  ]
}