{
  "update_time": "2026-06-02 18:04:19",
  "count": 2,
  "accounts": [
    {
      "account": "De***@icloud.com",
      "email": "DeborazpiHarr967@icloud.com",
      "fullEmail": "DeborazpiHarr967@icloud.com",
      "password": "x5Qt9ch9m9",
      "region": "US",
      "regionName": "美区",
      "status": "正常",
      "checkTime": "2026-06-02 18:04:18",
      "crawl_time": "2026-06-02 18:04:18",
      "source_page": "https://ccbaohe.com/appleID/"
    },
    {
      "account": "dm***@mail.com",
      "email": "dmomegurujuk95@mail.com",
      "fullEmail": "dmomegurujuk95@mail.com",
      "password": "ta6m7h8nAf",
      "region": "US",
      "regionName": "Unknown",
      "status": "正常",
      "checkTime": "2026-06-02 18:04:18",
      "crawl_time": "2026-06-02 18:04:18",
      "source_page": "https://ccbaohe.com/appleID/"
    }
  ]
}