{
  "update_time": "2026-04-22 15:51:34",
  "count": 2,
  "accounts": [
    {
      "account": "ZB***@js002.club",
      "email": "ZBn6jwPE@js002.club",
      "fullEmail": "ZBn6jwPE@js002.club",
      "password": "gg2HzS3Emx",
      "region": "US",
      "regionName": "未知",
      "status": "正常",
      "checkTime": "2026-04-22 15:51:30",
      "crawl_time": "2026-04-22 15:51:30",
      "source_page": "https://tkbaohe.com/Shadowrocket/"
    },
    {
      "account": "Th***@outlook.com",
      "email": "ThomasMccoy4240@outlook.com",
      "fullEmail": "ThomasMccoy4240@outlook.com",
      "password": "pmweYKP9Ge",
      "region": "US",
      "regionName": "美国",
      "status": "正常",
      "checkTime": "2026-04-22 15:51:34",
      "crawl_time": "2026-04-22 15:51:34",
      "source_page": "https://ccbaohe.com/appleID/"
    }
  ]
}