{
  "update_time": "2026-05-10 22:34:59",
  "count": 2,
  "accounts": [
    {
      "account": "Lu***@icloud.com",
      "email": "LuilyLqynch86906@icloud.com",
      "fullEmail": "LuilyLqynch86906@icloud.com",
      "password": "KmjYSe3AJ5",
      "region": "US",
      "regionName": "美国",
      "status": "正常",
      "checkTime": "2026-05-10 22:34:59",
      "crawl_time": "2026-05-10 22:34:59",
      "source_page": "https://ccbaohe.com/appleID/"
    },
    {
      "account": "mu***@outlook.com",
      "email": "murphylangworthck@outlook.com",
      "fullEmail": "murphylangworthck@outlook.com",
      "password": "g9S9TtV3QZ",
      "region": "US",
      "regionName": "越南-🇻🇳",
      "status": "正常",
      "checkTime": "2026-05-10 22:34:55",
      "crawl_time": "2026-05-10 22:34:55",
      "source_page": "https://tkbaohe.com/Shadowrocket/"
    }
  ]
}